{"value": [{"zip_code":"22311","country":"US","city":"Alexandria","state":"Virginia","state_ab":"VA","county":"Alexandria (city)","geo_location":{"type": "Point", "coordinates": [38.832,-77.12]}},
{"zip_code":"24201","country":"US","city":"Bristol","state":"Virginia","state_ab":"VA","county":"Bristol (city)","geo_location":{"type": "Point", "coordinates": [36.6181,-82.1823]}},
{"zip_code":"22904","country":"US","city":"Charlottesville","state":"Virginia","state_ab":"VA","county":"Charlottesville (city)","geo_location":{"type": "Point", "coordinates": [38.0401,-78.4851]}},
{"zip_code":"23327","country":"US","city":"Chesapeake","state":"Virginia","state_ab":"VA","county":"Chesapeake (city)","geo_location":{"type": "Point", "coordinates": [36.7085,-76.2785]}},
{"zip_code":"22401","country":"US","city":"Fredericksburg","state":"Virginia","state_ab":"VA","county":"Fredericksburg (city)","geo_location":{"type": "Point", "coordinates": [38.2995,-77.4772]}},
{"zip_code":"23651","country":"US","city":"Fort Monroe","state":"Virginia","state_ab":"VA","county":"Hampton (city)","geo_location":{"type": "Point", "coordinates": [37.018,-76.3044]}},
{"zip_code":"23664","country":"US","city":"Hampton","state":"Virginia","state_ab":"VA","county":"Hampton (city)","geo_location":{"type": "Point", "coordinates": [37.0566,-76.2966]}},
{"zip_code":"22801","country":"US","city":"Harrisonburg","state":"Virginia","state_ab":"VA","county":"Harrisonburg (city)","geo_location":{"type": "Point", "coordinates": [38.4489,-78.8714]}},
{"zip_code":"20111","country":"US","city":"Manassas","state":"Virginia","state_ab":"VA","county":"Manassas Park (city)","geo_location":{"type": "Point", "coordinates": [38.7707,-77.4494]}},
{"zip_code":"23507","country":"US","city":"Norfolk","state":"Virginia","state_ab":"VA","county":"Norfolk (city)","geo_location":{"type": "Point", "coordinates": [36.8645,-76.3004]}},
{"zip_code":"23804","country":"US","city":"Petersburg","state":"Virginia","state_ab":"VA","county":"Petersburg (city)","geo_location":{"type": "Point", "coordinates": [37.2048,-77.3928]}},
{"zip_code":"23701","country":"US","city":"Portsmouth","state":"Virginia","state_ab":"VA","county":"Portsmouth (city)","geo_location":{"type": "Point", "coordinates": [36.8089,-76.3671]}},
{"zip_code":"23211","country":"US","city":"Richmond","state":"Virginia","state_ab":"VA","county":"City of Richmond","geo_location":{"type": "Point", "coordinates": [37.5593,-77.4471]}},
{"zip_code":"23224","country":"US","city":"Richmond","state":"Virginia","state_ab":"VA","county":"Richmond (city)","geo_location":{"type": "Point", "coordinates": [37.4955,-77.471]}},
{"zip_code":"23277","country":"US","city":"Richmond","state":"Virginia","state_ab":"VA","county":"City of Richmond","geo_location":{"type": "Point", "coordinates": [37.5535,-77.4604]}},
{"zip_code":"23291","country":"US","city":"Richmond","state":"Virginia","state_ab":"VA","county":"Richmond (city)","geo_location":{"type": "Point", "coordinates": [37.5242,-77.4932]}},
{"zip_code":"24007","country":"US","city":"Roanoke","state":"Virginia","state_ab":"VA","county":"Roanoke (city)","geo_location":{"type": "Point", "coordinates": [37.2742,-79.9579]}},
{"zip_code":"24034","country":"US","city":"Roanoke","state":"Virginia","state_ab":"VA","county":"Roanoke (city)","geo_location":{"type": "Point", "coordinates": [37.2742,-79.9579]}},
{"zip_code":"23457","country":"US","city":"Virginia Beach","state":"Virginia","state_ab":"VA","county":"Virginia Beach (city)","geo_location":{"type": "Point", "coordinates": [36.6224,-76.0249]}},
{"zip_code":"23471","country":"US","city":"Virginia Beach","state":"Virginia","state_ab":"VA","county":"Virginia Beach (city)","geo_location":{"type": "Point", "coordinates": [36.7957,-76.0126]}},
{"zip_code":"23521","country":"US","city":"Norfolk","state":"Virginia","state_ab":"VA","county":"Virginia Beach (city)","geo_location":{"type": "Point", "coordinates": [36.9131,-76.1472]}},
{"zip_code":"23187","country":"US","city":"Williamsburg","state":"Virginia","state_ab":"VA","county":"Williamsburg (city)","geo_location":{"type": "Point", "coordinates": [37.3105,-76.7468]}},
{"zip_code":"5251","country":"US","city":"Dorset","state":"Vermont","state_ab":"VT","county":"Bennington","geo_location":{"type": "Point", "coordinates": [43.2636,-73.0766]}},
{"zip_code":"5871","country":"US","city":"West Burke","state":"Vermont","state_ab":"VT","county":"Caledonia","geo_location":{"type": "Point", "coordinates": [44.6636,-71.9572]}},
{"zip_code":"5404","country":"US","city":"Winooski","state":"Vermont","state_ab":"VT","county":"Chittenden","geo_location":{"type": "Point", "coordinates": [44.4949,-73.1874]}},
{"zip_code":"5907","country":"US","city":"Norton","state":"Vermont","state_ab":"VT","county":"Essex","geo_location":{"type": "Point", "coordinates": [44.9888,-71.7884]}},
{"zip_code":"5457","country":"US","city":"Franklin","state":"Vermont","state_ab":"VT","county":"Franklin","geo_location":{"type": "Point", "coordinates": [44.9614,-72.9037]}},
{"zip_code":"5471","country":"US","city":"Montgomery Center","state":"Vermont","state_ab":"VT","county":"Franklin","geo_location":{"type": "Point", "coordinates": [44.8482,-72.6198]}},
{"zip_code":"5444","country":"US","city":"Cambridge","state":"Vermont","state_ab":"VT","county":"Lamoille","geo_location":{"type": "Point", "coordinates": [44.6222,-72.8812]}},
{"zip_code":"5044","country":"US","city":"Ely","state":"Vermont","state_ab":"VT","county":"Orange County","geo_location":{"type": "Point", "coordinates": [43.8764,-72.1769]}},
{"zip_code":"5857","country":"US","city":"Newport Center","state":"Vermont","state_ab":"VT","county":"Orleans","geo_location":{"type": "Point", "coordinates": [44.9442,-72.2974]}},
{"zip_code":"5701","country":"US","city":"Rutland","state":"Vermont","state_ab":"VT","county":"Rutland","geo_location":{"type": "Point", "coordinates": [43.6141,-72.9708]}},
{"zip_code":"5741","country":"US","city":"East Poultney","state":"Vermont","state_ab":"VT","county":"Rutland","geo_location":{"type": "Point", "coordinates": [43.592,-72.8181]}},
{"zip_code":"5651","country":"US","city":"East Montpelier","state":"Vermont","state_ab":"VT","county":"Washington","geo_location":{"type": "Point", "coordinates": [44.2828,-72.4926]}},
{"zip_code":"5664","country":"US","city":"Northfield Falls","state":"Vermont","state_ab":"VT","county":"Washington","geo_location":{"type": "Point", "coordinates": [44.1835,-72.6466]}},
{"zip_code":"5677","country":"US","city":"Waterbury Center","state":"Vermont","state_ab":"VT","county":"Washington","geo_location":{"type": "Point", "coordinates": [44.3828,-72.708]}},
{"zip_code":"5301","country":"US","city":"Brattleboro","state":"Vermont","state_ab":"VT","county":"Windham","geo_location":{"type": "Point", "coordinates": [42.8574,-72.5933]}},
{"zip_code":"5341","country":"US","city":"East Dover","state":"Vermont","state_ab":"VT","county":"Windham","geo_location":{"type": "Point", "coordinates": [42.9505,-72.783]}},
{"zip_code":"5354","country":"US","city":"Vernon","state":"Vermont","state_ab":"VT","county":"Windham","geo_location":{"type": "Point", "coordinates": [42.7565,-72.5115]}},
{"zip_code":"5031","country":"US","city":"Barnard","state":"Vermont","state_ab":"VT","county":"Windsor","geo_location":{"type": "Point", "coordinates": [43.6576,-72.5459]}},
{"zip_code":"5071","country":"US","city":"South Woodstock","state":"Vermont","state_ab":"VT","county":"Windsor","geo_location":{"type": "Point", "coordinates": [43.5601,-72.5384]}},
{"zip_code":"5084","country":"US","city":"West Hartford","state":"Vermont","state_ab":"VT","county":"Windsor","geo_location":{"type": "Point", "coordinates": [43.7185,-72.4439]}},
{"zip_code":"5161","country":"US","city":"Weston","state":"Vermont","state_ab":"VT","county":"Windsor","geo_location":{"type": "Point", "coordinates": [43.2941,-72.7935]}},
{"zip_code":"5767","country":"US","city":"Rochester","state":"Vermont","state_ab":"VT","county":"Windsor","geo_location":{"type": "Point", "coordinates": [43.8804,-72.8159]}},
{"zip_code":"99344","country":"US","city":"Othello","state":"Washington","state_ab":"WA","county":"Adams","geo_location":{"type": "Point", "coordinates": [46.8527,-118.9932]}},
{"zip_code":"99371","country":"US","city":"Washtucna","state":"Washington","state_ab":"WA","county":"Adams","geo_location":{"type": "Point", "coordinates": [46.8209,-118.2862]}},
{"zip_code":"98817","country":"US","city":"Chelan Falls","state":"Washington","state_ab":"WA","county":"Chelan","geo_location":{"type": "Point", "coordinates": [47.8418,-119.9579]}},
{"zip_code":"98831","country":"US","city":"Manson","state":"Washington","state_ab":"WA","county":"Chelan","geo_location":{"type": "Point", "coordinates": [47.8958,-120.149]}},
{"zip_code":"98381","country":"US","city":"Sekiu","state":"Washington","state_ab":"WA","county":"Clallam","geo_location":{"type": "Point", "coordinates": [48.3032,-124.4685]}},
{"zip_code":"98664","country":"US","city":"Vancouver","state":"Washington","state_ab":"WA","county":"Clark","geo_location":{"type": "Point", "coordinates": [45.6231,-122.5767]}},
{"zip_code":"98611","country":"US","city":"Castle Rock","state":"Washington","state_ab":"WA","county":"Cowlitz","geo_location":{"type": "Point", "coordinates": [46.2783,-122.9139]}},
{"zip_code":"98857","country":"US","city":"Warden","state":"Washington","state_ab":"WA","county":"Grant","geo_location":{"type": "Point", "coordinates": [46.977,-119.0539]}},
{"zip_code":"99357","country":"US","city":"Royal City","state":"Washington","state_ab":"WA","county":"Grant","geo_location":{"type": "Point", "coordinates": [46.9156,-119.5815]}},
{"zip_code":"98547","country":"US","city":"Grayland","state":"Washington","state_ab":"WA","county":"Grays Harbor","geo_location":{"type": "Point", "coordinates": [46.8264,-124.094]}},
{"zip_code":"98587","country":"US","city":"Taholah","state":"Washington","state_ab":"WA","county":"Grays Harbor","geo_location":{"type": "Point", "coordinates": [47.3407,-124.2827]}},
{"zip_code":"98277","country":"US","city":"Oak Harbor","state":"Washington","state_ab":"WA","county":"Island","geo_location":{"type": "Point", "coordinates": [48.3151,-122.6374]}},
{"zip_code":"98004","country":"US","city":"Bellevue","state":"Washington","state_ab":"WA","county":"King","geo_location":{"type": "Point", "coordinates": [47.6155,-122.2072]}},
{"zip_code":"98031","country":"US","city":"Kent","state":"Washington","state_ab":"WA","county":"King","geo_location":{"type": "Point", "coordinates": [47.388,-122.1932]}},
{"zip_code":"98057","country":"US","city":"Renton","state":"Washington","state_ab":"WA","county":"King","geo_location":{"type": "Point", "coordinates": [47.4714,-122.2203]}},
{"zip_code":"98071","country":"US","city":"Auburn","state":"Washington","state_ab":"WA","county":"King","geo_location":{"type": "Point", "coordinates": [47.4323,-121.8034]}},
{"zip_code":"98107","country":"US","city":"Seattle","state":"Washington","state_ab":"WA","county":"King","geo_location":{"type": "Point", "coordinates": [47.6701,-122.3763]}},
{"zip_code":"98121","country":"US","city":"Seattle","state":"Washington","state_ab":"WA","county":"King","geo_location":{"type": "Point", "coordinates": [47.6151,-122.3447]}},
{"zip_code":"98134","country":"US","city":"Seattle","state":"Washington","state_ab":"WA","county":"King","geo_location":{"type": "Point", "coordinates": [47.5903,-122.3263]}},
{"zip_code":"98161","country":"US","city":"Seattle","state":"Washington","state_ab":"WA","county":"King","geo_location":{"type": "Point", "coordinates": [47.4323,-121.8034]}},
{"zip_code":"98174","country":"US","city":"Seattle","state":"Washington","state_ab":"WA","county":"King","geo_location":{"type": "Point", "coordinates": [47.4323,-121.8034]}},
{"zip_code":"98224","country":"US","city":"Baring","state":"Washington","state_ab":"WA","county":"King","geo_location":{"type": "Point", "coordinates": [47.7671,-121.4814]}},
{"zip_code":"98314","country":"US","city":"Bremerton","state":"Washington","state_ab":"WA","county":"Kitsap","geo_location":{"type": "Point", "coordinates": [47.5593,-122.6492]}},
{"zip_code":"98367","country":"US","city":"Port Orchard","state":"Washington","state_ab":"WA","county":"Kitsap","geo_location":{"type": "Point", "coordinates": [47.4707,-122.651]}},
{"zip_code":"98934","country":"US","city":"Kittitas","state":"Washington","state_ab":"WA","county":"Kittitas","geo_location":{"type": "Point", "coordinates": [46.9806,-120.4163]}},
{"zip_code":"98844","country":"US","city":"Oroville","state":"Washington","state_ab":"WA","county":"Okanogan","geo_location":{"type": "Point", "coordinates": [48.9397,-119.4032]}},
{"zip_code":"99124","country":"US","city":"Elmer City","state":"Washington","state_ab":"WA","county":"Okanogan","geo_location":{"type": "Point", "coordinates": [48.0154,-118.9549]}},
{"zip_code":"98561","country":"US","city":"Menlo","state":"Washington","state_ab":"WA","county":"Pacific","geo_location":{"type": "Point", "coordinates": [46.5146,-123.769]}},
{"zip_code":"98624","country":"US","city":"Ilwaco","state":"Washington","state_ab":"WA","county":"Pacific","geo_location":{"type": "Point", "coordinates": [46.3142,-124.0282]}},
{"zip_code":"98637","country":"US","city":"Nahcotta","state":"Washington","state_ab":"WA","county":"Pacific","geo_location":{"type": "Point", "coordinates": [46.5146,-123.769]}},
{"zip_code":"98327","country":"US","city":"Dupont","state":"Washington","state_ab":"WA","county":"Pierce","geo_location":{"type": "Point", "coordinates": [47.0909,-122.6567]}},
{"zip_code":"98354","country":"US","city":"Milton","state":"Washington","state_ab":"WA","county":"Pierce","geo_location":{"type": "Point", "coordinates": [47.2483,-122.3155]}},
{"zip_code":"98394","country":"US","city":"Vaughn","state":"Washington","state_ab":"WA","county":"Pierce","geo_location":{"type": "Point", "coordinates": [47.3309,-122.7736]}},
{"zip_code":"98404","country":"US","city":"Tacoma","state":"Washington","state_ab":"WA","county":"Pierce","geo_location":{"type": "Point", "coordinates": [47.2113,-122.4126]}},
{"zip_code":"98417","country":"US","city":"Tacoma","state":"Washington","state_ab":"WA","county":"Pierce County","geo_location":{"type": "Point", "coordinates": [47.2061,-122.4822]}},
{"zip_code":"98431","country":"US","city":"Tacoma","state":"Washington","state_ab":"WA","county":"Pierce","geo_location":{"type": "Point", "coordinates": [47.0662,-122.1132]}},
{"zip_code":"98444","country":"US","city":"Tacoma","state":"Washington","state_ab":"WA","county":"Pierce","geo_location":{"type": "Point", "coordinates": [47.1464,-122.4572]}},
{"zip_code":"98471","country":"US","city":"Tacoma","state":"Washington","state_ab":"WA","county":"Pierce","geo_location":{"type": "Point", "coordinates": [47.0662,-122.1132]}},
{"zip_code":"98497","country":"US","city":"Lakewood","state":"Washington","state_ab":"WA","county":"Pierce","geo_location":{"type": "Point", "coordinates": [47.0662,-122.1132]}},
{"zip_code":"98237","country":"US","city":"Concrete","state":"Washington","state_ab":"WA","county":"Skagit","geo_location":{"type": "Point", "coordinates": [48.531,-121.6643]}},
{"zip_code":"98651","country":"US","city":"Underwood","state":"Washington","state_ab":"WA","county":"Skamania","geo_location":{"type": "Point", "coordinates": [45.7409,-121.5974]}},
{"zip_code":"98251","country":"US","city":"Gold Bar","state":"Washington","state_ab":"WA","county":"Snohomish","geo_location":{"type": "Point", "coordinates": [47.8331,-121.6365]}},
{"zip_code":"98291","country":"US","city":"Snohomish","state":"Washington","state_ab":"WA","county":"Snohomish","geo_location":{"type": "Point", "coordinates": [47.9095,-122.0501]}},
{"zip_code":"99021","country":"US","city":"Mead","state":"Washington","state_ab":"WA","county":"Spokane","geo_location":{"type": "Point", "coordinates": [47.7933,-117.3117]}},
{"zip_code":"99201","country":"US","city":"Spokane","state":"Washington","state_ab":"WA","county":"Spokane","geo_location":{"type": "Point", "coordinates": [47.6665,-117.4365]}},
{"zip_code":"99214","country":"US","city":"Spokane","state":"Washington","state_ab":"WA","county":"Spokane","geo_location":{"type": "Point", "coordinates": [47.6536,-117.4317]}},
{"zip_code":"99254","country":"US","city":"Spokane","state":"Washington","state_ab":"WA","county":"Spokane County","geo_location":{"type": "Point", "coordinates": [47.6581,-117.424]}},
{"zip_code":"99034","country":"US","city":"Tumtum","state":"Washington","state_ab":"WA","county":"Stevens","geo_location":{"type": "Point", "coordinates": [47.8941,-117.7536]}},
{"zip_code":"99137","country":"US","city":"Hunters","state":"Washington","state_ab":"WA","county":"Stevens","geo_location":{"type": "Point", "coordinates": [48.1333,-118.1525]}},
{"zip_code":"99151","country":"US","city":"Marcus","state":"Washington","state_ab":"WA","county":"Stevens","geo_location":{"type": "Point", "coordinates": [48.7868,-117.924]}},
{"zip_code":"98507","country":"US","city":"Olympia","state":"Washington","state_ab":"WA","county":"Thurston","geo_location":{"type": "Point", "coordinates": [46.9781,-122.7024]}},
{"zip_code":"98264","country":"US","city":"Lynden","state":"Washington","state_ab":"WA","county":"Whatcom","geo_location":{"type": "Point", "coordinates": [48.9372,-122.4592]}},
{"zip_code":"99111","country":"US","city":"Colfax","state":"Washington","state_ab":"WA","county":"Whitman","geo_location":{"type": "Point", "coordinates": [46.88,-117.367]}},
{"zip_code":"99164","country":"US","city":"Pullman","state":"Washington","state_ab":"WA","county":"Whitman","geo_location":{"type": "Point", "coordinates": [46.8387,-117.6443]}},
{"zip_code":"98907","country":"US","city":"Yakima","state":"Washington","state_ab":"WA","county":"Yakima","geo_location":{"type": "Point", "coordinates": [46.6288,-120.574]}},
{"zip_code":"98921","country":"US","city":"Buena","state":"Washington","state_ab":"WA","county":"Yakima","geo_location":{"type": "Point", "coordinates": [46.4212,-120.3151]}},
{"zip_code":"98947","country":"US","city":"Tieton","state":"Washington","state_ab":"WA","county":"Yakima","geo_location":{"type": "Point", "coordinates": [46.7063,-120.7473]}},
{"zip_code":"54857","country":"US","city":"Mikana","state":"Wisconsin","state_ab":"WI","county":"Barron","geo_location":{"type": "Point", "coordinates": [45.6096,-91.6196]}},
{"zip_code":"54844","country":"US","city":"Herbster","state":"Wisconsin","state_ab":"WI","county":"Bayfield","geo_location":{"type": "Point", "coordinates": [46.8213,-91.2332]}},
{"zip_code":"54301","country":"US","city":"Green Bay","state":"Wisconsin","state_ab":"WI","county":"Brown","geo_location":{"type": "Point", "coordinates": [44.482,-88.0205]}},
{"zip_code":"53014","country":"US","city":"Chilton","state":"Wisconsin","state_ab":"WI","county":"Calumet","geo_location":{"type": "Point", "coordinates": [44.0242,-88.1827]}},
{"zip_code":"54727","country":"US","city":"Cadott","state":"Wisconsin","state_ab":"WI","county":"Chippewa","geo_location":{"type": "Point", "coordinates": [44.963,-91.1699]}},
{"zip_code":"53957","country":"US","city":"Randolph","state":"Wisconsin","state_ab":"WI","county":"Columbia","geo_location":{"type": "Point", "coordinates": [43.5352,-89.0068]}},
{"zip_code":"53517","country":"US","city":"Blue Mounds","state":"Wisconsin","state_ab":"WI","county":"Dane","geo_location":{"type": "Point", "coordinates": [43.005,-89.8345]}},
{"zip_code":"53531","country":"US","city":"Deerfield","state":"Wisconsin","state_ab":"WI","county":"Dane","geo_location":{"type": "Point", "coordinates": [43.0571,-89.0862]}},
{"zip_code":"53571","country":"US","city":"Morrisonville","state":"Wisconsin","state_ab":"WI","county":"Dane","geo_location":{"type": "Point", "coordinates": [43.2773,-89.3564]}},
{"zip_code":"53597","country":"US","city":"Waunakee","state":"Wisconsin","state_ab":"WI","county":"Dane","geo_location":{"type": "Point", "coordinates": [43.1818,-89.4532]}},
{"zip_code":"53711","country":"US","city":"Madison","state":"Wisconsin","state_ab":"WI","county":"Dane","geo_location":{"type": "Point", "coordinates": [43.0356,-89.4526]}},
{"zip_code":"53777","country":"US","city":"Madison","state":"Wisconsin","state_ab":"WI","county":"Dane","geo_location":{"type": "Point", "coordinates": [43.0696,-89.4239]}},
{"zip_code":"53791","country":"US","city":"Madison","state":"Wisconsin","state_ab":"WI","county":"Dane","geo_location":{"type": "Point", "coordinates": [43.0696,-89.4239]}},
{"zip_code":"53557","country":"US","city":"Lowell","state":"Wisconsin","state_ab":"WI","county":"Dodge","geo_location":{"type": "Point", "coordinates": [43.342,-88.7873]}},
{"zip_code":"53917","country":"US","city":"Beaver Dam","state":"Wisconsin","state_ab":"WI","county":"Dodge","geo_location":{"type": "Point", "coordinates": [43.4142,-88.7049]}},
{"zip_code":"54211","country":"US","city":"Ephraim","state":"Wisconsin","state_ab":"WI","county":"Door","geo_location":{"type": "Point", "coordinates": [45.1592,-87.171]}},
{"zip_code":"54701","country":"US","city":"Eau Claire","state":"Wisconsin","state_ab":"WI","county":"Eau Claire","geo_location":{"type": "Point", "coordinates": [44.784,-91.4877]}},
{"zip_code":"54741","country":"US","city":"Fairchild","state":"Wisconsin","state_ab":"WI","county":"Eau Claire","geo_location":{"type": "Point", "coordinates": [44.5963,-90.9906]}},
{"zip_code":"54121","country":"US","city":"Florence","state":"Wisconsin","state_ab":"WI","county":"Florence","geo_location":{"type": "Point", "coordinates": [45.9027,-88.2289]}},
{"zip_code":"53931","country":"US","city":"Fairwater","state":"Wisconsin","state_ab":"WI","county":"Fond du Lac","geo_location":{"type": "Point", "coordinates": [43.7475,-88.8665]}},
{"zip_code":"54974","country":"US","city":"Rosendale","state":"Wisconsin","state_ab":"WI","county":"Fond du Lac","geo_location":{"type": "Point", "coordinates": [43.7889,-88.6417]}},
{"zip_code":"53801","country":"US","city":"Bagley","state":"Wisconsin","state_ab":"WI","county":"Grant","geo_location":{"type": "Point", "coordinates": [42.9207,-91.0685]}},
{"zip_code":"53827","country":"US","city":"Woodman","state":"Wisconsin","state_ab":"WI","county":"Grant","geo_location":{"type": "Point", "coordinates": [43.0577,-90.8245]}},
{"zip_code":"53544","country":"US","city":"Hollandale","state":"Wisconsin","state_ab":"WI","county":"Iowa","geo_location":{"type": "Point", "coordinates": [42.8773,-89.913]}},
{"zip_code":"54534","country":"US","city":"Hurley","state":"Wisconsin","state_ab":"WI","county":"Iron","geo_location":{"type": "Point", "coordinates": [46.4448,-90.1975]}},
{"zip_code":"54547","country":"US","city":"Mercer","state":"Wisconsin","state_ab":"WI","county":"Iron","geo_location":{"type": "Point", "coordinates": [46.1696,-90.0679]}},
{"zip_code":"54611","country":"US","city":"Alma Center","state":"Wisconsin","state_ab":"WI","county":"Jackson","geo_location":{"type": "Point", "coordinates": [44.4452,-90.9356]}},
{"zip_code":"54754","country":"US","city":"Merrillan","state":"Wisconsin","state_ab":"WI","county":"Jackson","geo_location":{"type": "Point", "coordinates": [44.4369,-90.8105]}},
{"zip_code":"53094","country":"US","city":"Watertown","state":"Wisconsin","state_ab":"WI","county":"Jefferson","geo_location":{"type": "Point", "coordinates": [43.193,-88.7185]}},
{"zip_code":"53944","country":"US","city":"Lyndon Station","state":"Wisconsin","state_ab":"WI","county":"Juneau","geo_location":{"type": "Point", "coordinates": [43.6899,-89.8915]}},
{"zip_code":"54637","country":"US","city":"Hustler","state":"Wisconsin","state_ab":"WI","county":"Juneau","geo_location":{"type": "Point", "coordinates": [43.8801,-90.2729]}},
{"zip_code":"53104","country":"US","city":"Bristol","state":"Wisconsin","state_ab":"WI","county":"Kenosha","geo_location":{"type": "Point", "coordinates": [42.5325,-88.0478]}},
{"zip_code":"53144","country":"US","city":"Kenosha","state":"Wisconsin","state_ab":"WI","county":"Kenosha","geo_location":{"type": "Point", "coordinates": [42.6058,-87.8762]}},
{"zip_code":"53171","country":"US","city":"Somers","state":"Wisconsin","state_ab":"WI","county":"Kenosha","geo_location":{"type": "Point", "coordinates": [42.6423,-87.9032]}},
{"zip_code":"53504","country":"US","city":"Argyle","state":"Wisconsin","state_ab":"WI","county":"Lafayette","geo_location":{"type": "Point", "coordinates": [42.6955,-89.8598]}},
{"zip_code":"54444","country":"US","city":"Kempster","state":"Wisconsin","state_ab":"WI","county":"Langlade","geo_location":{"type": "Point", "coordinates": [45.2494,-89.0321]}},
{"zip_code":"54417","country":"US","city":"Brokaw","state":"Wisconsin","state_ab":"WI","county":"Marathon","geo_location":{"type": "Point", "coordinates": [45.0273,-89.6541]}},
{"zip_code":"54471","country":"US","city":"Ringle","state":"Wisconsin","state_ab":"WI","county":"Marathon","geo_location":{"type": "Point", "coordinates": [44.9238,-89.4328]}},
{"zip_code":"54484","country":"US","city":"Stratford","state":"Wisconsin","state_ab":"WI","county":"Marathon","geo_location":{"type": "Point", "coordinates": [44.7899,-90.0583]}},
{"zip_code":"54161","country":"US","city":"Pound","state":"Wisconsin","state_ab":"WI","county":"Marinette","geo_location":{"type": "Point", "coordinates": [45.1273,-88.1396]}},
{"zip_code":"53207","country":"US","city":"Milwaukee","state":"Wisconsin","state_ab":"WI","county":"Milwaukee","geo_location":{"type": "Point", "coordinates": [42.9751,-87.8947]}},
{"zip_code":"45404","country":"US","city":"Dayton","state":"Ohio","state_ab":"OH","county":"Montgomery","geo_location":{"type": "Point", "coordinates": [39.7862,-84.1622]}},
{"zip_code":"45417","country":"US","city":"Dayton","state":"Ohio","state_ab":"OH","county":"Montgomery","geo_location":{"type": "Point", "coordinates": [39.7528,-84.247]}},
{"zip_code":"45444","country":"US","city":"Dayton","state":"Ohio","state_ab":"OH","county":"Montgomery County","geo_location":{"type": "Point", "coordinates": [39.7159,-84.1403]}},
{"zip_code":"43787","country":"US","city":"Stockport","state":"Ohio","state_ab":"OH","county":"Morgan","geo_location":{"type": "Point", "coordinates": [39.549,-81.8262]}},
{"zip_code":"43321","country":"US","city":"Fulton","state":"Ohio","state_ab":"OH","county":"Morrow","geo_location":{"type": "Point", "coordinates": [40.4971,-82.8342]}},
{"zip_code":"43334","country":"US","city":"Marengo","state":"Ohio","state_ab":"OH","county":"Morrow","geo_location":{"type": "Point", "coordinates": [40.3895,-82.8121]}},
{"zip_code":"43734","country":"US","city":"Duncan Falls","state":"Ohio","state_ab":"OH","county":"Muskingum","geo_location":{"type": "Point", "coordinates": [39.8778,-81.9117]}},
{"zip_code":"45727","country":"US","city":"Dexter City","state":"Ohio","state_ab":"OH","county":"Noble","geo_location":{"type": "Point", "coordinates": [39.6526,-81.4672]}},
{"zip_code":"43761","country":"US","city":"Moxahala","state":"Ohio","state_ab":"OH","county":"Perry","geo_location":{"type": "Point", "coordinates": [39.7403,-82.2484]}},
{"zip_code":"45624","country":"US","city":"Cynthiana","state":"Ohio","state_ab":"OH","county":"Pike","geo_location":{"type": "Point", "coordinates": [39.1638,-83.3429]}},
{"zip_code":"44234","country":"US","city":"Hiram","state":"Ohio","state_ab":"OH","county":"Portage","geo_location":{"type": "Point", "coordinates": [41.3323,-81.1464]}},
{"zip_code":"45381","country":"US","city":"West Alexandria","state":"Ohio","state_ab":"OH","county":"Preble","geo_location":{"type": "Point", "coordinates": [39.7259,-84.5352]}},
{"zip_code":"45831","country":"US","city":"Continental","state":"Ohio","state_ab":"OH","county":"Putnam","geo_location":{"type": "Point", "coordinates": [41.1148,-84.2358]}},
{"zip_code":"45844","country":"US","city":"Fort Jennings","state":"Ohio","state_ab":"OH","county":"Putnam","geo_location":{"type": "Point", "coordinates": [40.9484,-84.2374]}},
{"zip_code":"44904","country":"US","city":"Mansfield","state":"Ohio","state_ab":"OH","county":"Richland","geo_location":{"type": "Point", "coordinates": [40.6824,-82.5286]}},
{"zip_code":"43101","country":"US","city":"Adelphi","state":"Ohio","state_ab":"OH","county":"Ross","geo_location":{"type": "Point", "coordinates": [39.4665,-82.7547]}},
{"zip_code":"43464","country":"US","city":"Vickery","state":"Ohio","state_ab":"OH","county":"Sandusky","geo_location":{"type": "Point", "coordinates": [41.391,-82.899]}},
{"zip_code":"45677","country":"US","city":"Scioto Furnace","state":"Ohio","state_ab":"OH","county":"Scioto","geo_location":{"type": "Point", "coordinates": [38.7941,-82.7555]}},
{"zip_code":"44801","country":"US","city":"Adrian","state":"Ohio","state_ab":"OH","county":"Seneca","geo_location":{"type": "Point", "coordinates": [41.0907,-83.3654]}},
{"zip_code":"44841","country":"US","city":"Kansas","state":"Ohio","state_ab":"OH","county":"Seneca","geo_location":{"type": "Point", "coordinates": [41.2512,-83.306]}},
{"zip_code":"44867","country":"US","city":"Republic","state":"Ohio","state_ab":"OH","county":"Seneca","geo_location":{"type": "Point", "coordinates": [41.1259,-83.0194]}},
{"zip_code":"45367","country":"US","city":"Sidney","state":"Ohio","state_ab":"OH","county":"Shelby","geo_location":{"type": "Point", "coordinates": [40.3336,-84.2183]}},
{"zip_code":"44647","country":"US","city":"Massillon","state":"Ohio","state_ab":"OH","county":"Stark","geo_location":{"type": "Point", "coordinates": [40.7959,-81.5533]}},
{"zip_code":"44711","country":"US","city":"Canton","state":"Ohio","state_ab":"OH","county":"Stark","geo_location":{"type": "Point", "coordinates": [40.8118,-81.3683]}},
{"zip_code":"44067","country":"US","city":"Northfield","state":"Ohio","state_ab":"OH","county":"Summit","geo_location":{"type": "Point", "coordinates": [41.3208,-81.5429]}},
{"zip_code":"44221","country":"US","city":"Cuyahoga Falls","state":"Ohio","state_ab":"OH","county":"Summit","geo_location":{"type": "Point", "coordinates": [41.1401,-81.479]}},
{"zip_code":"44311","country":"US","city":"Akron","state":"Ohio","state_ab":"OH","county":"Summit","geo_location":{"type": "Point", "coordinates": [41.0638,-81.52]}},
{"zip_code":"44481","country":"US","city":"Warren","state":"Ohio","state_ab":"OH","county":"Trumbull","geo_location":{"type": "Point", "coordinates": [41.1724,-80.8718]}},
{"zip_code":"43837","country":"US","city":"Port Washington","state":"Ohio","state_ab":"OH","county":"Tuscarawas","geo_location":{"type": "Point", "coordinates": [40.3404,-81.5215]}},
{"zip_code":"44621","country":"US","city":"Dennison","state":"Ohio","state_ab":"OH","county":"Tuscarawas","geo_location":{"type": "Point", "coordinates": [40.4089,-81.3203]}},
{"zip_code":"43077","country":"US","city":"Unionville Center","state":"Ohio","state_ab":"OH","county":"Union","geo_location":{"type": "Point", "coordinates": [40.1367,-83.3408]}},
{"zip_code":"45651","country":"US","city":"Mc Arthur","state":"Ohio","state_ab":"OH","county":"Vinton","geo_location":{"type": "Point", "coordinates": [39.28,-82.4753]}},
{"zip_code":"45714","country":"US","city":"Belpre","state":"Ohio","state_ab":"OH","county":"Washington","geo_location":{"type": "Point", "coordinates": [39.2868,-81.5968]}},
{"zip_code":"45767","country":"US","city":"New Matamoras","state":"Ohio","state_ab":"OH","county":"Washington","geo_location":{"type": "Point", "coordinates": [39.5288,-81.094]}},
{"zip_code":"44287","country":"US","city":"West Salem","state":"Ohio","state_ab":"OH","county":"Wayne","geo_location":{"type": "Point", "coordinates": [40.9485,-82.1066]}},
{"zip_code":"43501","country":"US","city":"Alvordton","state":"Ohio","state_ab":"OH","county":"Williams","geo_location":{"type": "Point", "coordinates": [41.6625,-84.4355]}},
{"zip_code":"43554","country":"US","city":"Pioneer","state":"Ohio","state_ab":"OH","county":"Williams","geo_location":{"type": "Point", "coordinates": [41.6656,-84.5363]}},
{"zip_code":"43437","country":"US","city":"Jerry City","state":"Ohio","state_ab":"OH","county":"Wood","geo_location":{"type": "Point", "coordinates": [41.2559,-83.6022]}},
{"zip_code":"43451","country":"US","city":"Portage","state":"Ohio","state_ab":"OH","county":"Wood","geo_location":{"type": "Point", "coordinates": [41.3127,-83.6143]}},
{"zip_code":"43541","country":"US","city":"Milton Center","state":"Ohio","state_ab":"OH","county":"Wood","geo_location":{"type": "Point", "coordinates": [41.3009,-83.8296]}},
{"zip_code":"73847","country":"US","city":"Knowles","state":"Oklahoma","state_ab":"OK","county":"Beaver","geo_location":{"type": "Point", "coordinates": [36.8393,-100.2179]}},
{"zip_code":"73627","country":"US","city":"Carter","state":"Oklahoma","state_ab":"OK","county":"Beckham","geo_location":{"type": "Point", "coordinates": [35.2208,-99.4822]}},
{"zip_code":"73744","country":"US","city":"Hitchcock","state":"Oklahoma","state_ab":"OK","county":"Blaine","geo_location":{"type": "Point", "coordinates": [35.9712,-98.3315]}},
{"zip_code":"74721","country":"US","city":"Albany","state":"Oklahoma","state_ab":"OK","county":"Bryan","geo_location":{"type": "Point", "coordinates": [33.922,-96.1918]}},
{"zip_code":"74747","country":"US","city":"Kemp","state":"Oklahoma","state_ab":"OK","county":"Bryan","geo_location":{"type": "Point", "coordinates": [33.773,-96.3555]}},
{"zip_code":"73047","country":"US","city":"Hinton","state":"Oklahoma","state_ab":"OK","county":"Caddo","geo_location":{"type": "Point", "coordinates": [35.4675,-98.3313]}},
{"zip_code":"73087","country":"US","city":"Tatums","state":"Oklahoma","state_ab":"OK","county":"Carter County","geo_location":{"type": "Point", "coordinates": [34.4826,-97.4612]}},
{"zip_code":"73487","country":"US","city":"Tatums","state":"Oklahoma","state_ab":"OK","county":"Carter","geo_location":{"type": "Point", "coordinates": [34.4777,-97.457]}},
{"zip_code":"74451","country":"US","city":"Park Hill","state":"Oklahoma","state_ab":"OK","county":"Cherokee","geo_location":{"type": "Point", "coordinates": [35.7977,-94.9822]}},
{"zip_code":"74464","country":"US","city":"Tahlequah","state":"Oklahoma","state_ab":"OK","county":"Cherokee","geo_location":{"type": "Point", "coordinates": [35.9094,-94.9787]}},
{"zip_code":"74761","country":"US","city":"Swink","state":"Oklahoma","state_ab":"OK","county":"Choctaw","geo_location":{"type": "Point", "coordinates": [33.9902,-95.1913]}},
{"zip_code":"73937","country":"US","city":"Felt","state":"Oklahoma","state_ab":"OK","county":"Cimarron","geo_location":{"type": "Point", "coordinates": [36.5666,-102.7974]}},
{"zip_code":"73601","country":"US","city":"Clinton","state":"Oklahoma","state_ab":"OK","county":"Custer","geo_location":{"type": "Point", "coordinates": [35.5115,-98.9795]}},
{"zip_code":"74347","country":"US","city":"Kansas","state":"Oklahoma","state_ab":"OK","county":"Delaware","geo_location":{"type": "Point", "coordinates": [36.2161,-94.8114]}},
{"zip_code":"73654","country":"US","city":"Leedey","state":"Oklahoma","state_ab":"OK","county":"Dewey","geo_location":{"type": "Point", "coordinates": [35.8698,-99.3491]}},
{"zip_code":"73667","country":"US","city":"Taloga","state":"Oklahoma","state_ab":"OK","county":"Dewey","geo_location":{"type": "Point", "coordinates": [35.9972,-98.9825]}},
{"zip_code":"73074","country":"US","city":"Paoli","state":"Oklahoma","state_ab":"OK","county":"Garvin","geo_location":{"type": "Point", "coordinates": [34.8285,-97.2608]}},
{"zip_code":"73771","country":"US","city":"Wakita","state":"Oklahoma","state_ab":"OK","county":"Grant","geo_location":{"type": "Point", "coordinates": [36.8753,-97.9427]}},
{"zip_code":"73834","country":"US","city":"Buffalo","state":"Oklahoma","state_ab":"OK","county":"Harper","geo_location":{"type": "Point", "coordinates": [36.8523,-99.5538]}},
{"zip_code":"74941","country":"US","city":"Keota","state":"Oklahoma","state_ab":"OK","county":"Haskell","geo_location":{"type": "Point", "coordinates": [35.2645,-94.9028]}},
{"zip_code":"73537","country":"US","city":"Eldorado","state":"Oklahoma","state_ab":"OK","county":"Jackson","geo_location":{"type": "Point", "coordinates": [34.4727,-99.646]}},
{"zip_code":"73447","country":"US","city":"Mannsville","state":"Oklahoma","state_ab":"OK","county":"Johnston","geo_location":{"type": "Point", "coordinates": [34.1899,-96.8778]}},
{"zip_code":"73461","country":"US","city":"Wapanucka","state":"Oklahoma","state_ab":"OK","county":"Johnston","geo_location":{"type": "Point", "coordinates": [34.3866,-96.4532]}},
{"zip_code":"74604","country":"US","city":"Ponca City","state":"Oklahoma","state_ab":"OK","county":"Kay","geo_location":{"type": "Point", "coordinates": [36.7299,-97.0454]}},
{"zip_code":"74631","country":"US","city":"Blackwell","state":"Oklahoma","state_ab":"OK","county":"Kay","geo_location":{"type": "Point", "coordinates": [36.8006,-97.2867]}},
{"zip_code":"73564","country":"US","city":"Roosevelt","state":"Oklahoma","state_ab":"OK","county":"Kiowa","geo_location":{"type": "Point", "coordinates": [34.847,-98.9836]}},
{"zip_code":"74901","country":"US","city":"Arkoma","state":"Oklahoma","state_ab":"OK","county":"Le Flore","geo_location":{"type": "Point", "coordinates": [35.3434,-94.4403]}},
{"zip_code":"74824","country":"US","city":"Agra","state":"Oklahoma","state_ab":"OK","county":"Lincoln","geo_location":{"type": "Point", "coordinates": [35.909,-96.8738]}},
{"zip_code":"74864","country":"US","city":"Prague","state":"Oklahoma","state_ab":"OK","county":"Lincoln","geo_location":{"type": "Point", "coordinates": [35.5105,-96.7009]}},
{"zip_code":"74734","country":"US","city":"Eagletown","state":"Oklahoma","state_ab":"OK","county":"McCurtain","geo_location":{"type": "Point", "coordinates": [34.0364,-94.5596]}},
{"zip_code":"74361","country":"US","city":"Pryor","state":"Oklahoma","state_ab":"OK","county":"Mayes","geo_location":{"type": "Point", "coordinates": [36.2921,-95.3129]}},
{"zip_code":"73061","country":"US","city":"Morrison","state":"Oklahoma","state_ab":"OK","county":"Noble","geo_location":{"type": "Point", "coordinates": [36.2902,-97.0228]}},
{"zip_code":"73757","country":"US","city":"Lucien","state":"Oklahoma","state_ab":"OK","county":"Noble","geo_location":{"type": "Point", "coordinates": [36.2753,-97.4526]}},
{"zip_code":"74644","country":"US","city":"Marland","state":"Oklahoma","state_ab":"OK","county":"Noble","geo_location":{"type": "Point", "coordinates": [36.5591,-97.0976]}},
{"zip_code":"73007","country":"US","city":"Arcadia","state":"Oklahoma","state_ab":"OK","county":"Oklahoma","geo_location":{"type": "Point", "coordinates": [35.6543,-97.3243]}},
{"zip_code":"73034","country":"US","city":"Edmond","state":"Oklahoma","state_ab":"OK","county":"Oklahoma","geo_location":{"type": "Point", "coordinates": [35.6665,-97.4798]}},
{"zip_code":"73111","country":"US","city":"Oklahoma City","state":"Oklahoma","state_ab":"OK","county":"Oklahoma","geo_location":{"type": "Point", "coordinates": [35.5042,-97.4806]}},
{"zip_code":"73124","country":"US","city":"Oklahoma City","state":"Oklahoma","state_ab":"OK","county":"Oklahoma","geo_location":{"type": "Point", "coordinates": [35.5514,-97.4075]}},
{"zip_code":"73137","country":"US","city":"Oklahoma City","state":"Oklahoma","state_ab":"OK","county":"Oklahoma","geo_location":{"type": "Point", "coordinates": [35.5514,-97.4075]}},
{"zip_code":"73151","country":"US","city":"Oklahoma City","state":"Oklahoma","state_ab":"OK","county":"Oklahoma","geo_location":{"type": "Point", "coordinates": [35.5676,-97.4111]}},
{"zip_code":"73164","country":"US","city":"Oklahoma City","state":"Oklahoma","state_ab":"OK","county":"Oklahoma","geo_location":{"type": "Point", "coordinates": [35.5514,-97.4075]}},
{"zip_code":"73177","country":"US","city":"Oklahoma City","state":"Oklahoma","state_ab":"OK","county":"Oklahoma","geo_location":{"type": "Point", "coordinates": [35.5514,-97.4075]}},
{"zip_code":"74437","country":"US","city":"Henryetta","state":"Oklahoma","state_ab":"OK","county":"Okmulgee","geo_location":{"type": "Point", "coordinates": [35.4622,-96.0122]}},
{"zip_code":"74127","country":"US","city":"Tulsa","state":"Oklahoma","state_ab":"OK","county":"Osage","geo_location":{"type": "Point", "coordinates": [36.1576,-96.0311]}},
{"zip_code":"74077","country":"US","city":"Stillwater","state":"Oklahoma","state_ab":"OK","county":"Payne","geo_location":{"type": "Point", "coordinates": [36.0937,-96.9875]}},
{"zip_code":"74501","country":"US","city":"Mcalester","state":"Oklahoma","state_ab":"OK","county":"Pittsburg","geo_location":{"type": "Point", "coordinates": [34.9262,-95.7592]}},
{"zip_code":"74554","country":"US","city":"Krebs","state":"Oklahoma","state_ab":"OK","county":"Pittsburg","geo_location":{"type": "Point", "coordinates": [34.9255,-95.7216]}},
{"zip_code":"74851","country":"US","city":"Mcloud","state":"Oklahoma","state_ab":"OK","county":"Pottawatomie","geo_location":{"type": "Point", "coordinates": [35.4262,-97.079]}},
{"zip_code":"74567","country":"US","city":"Snow","state":"Oklahoma","state_ab":"OK","county":"Pushmataha","geo_location":{"type": "Point", "coordinates": [34.4419,-95.4622]}},
{"zip_code":"74837","country":"US","city":"Cromwell","state":"Oklahoma","state_ab":"OK","county":"Seminole","geo_location":{"type": "Point", "coordinates": [35.3405,-96.4546]}},
{"zip_code":"74954","country":"US","city":"Roland","state":"Oklahoma","state_ab":"OK","county":"Sequoyah","geo_location":{"type": "Point", "coordinates": [35.4538,-94.5291]}},
{"zip_code":"73434","country":"US","city":"Foster","state":"Oklahoma","state_ab":"OK","county":"Stephens","geo_location":{"type": "Point", "coordinates": [34.6379,-97.5455]}},
{"zip_code":"73951","country":"US","city":"Tyrone","state":"Oklahoma","state_ab":"OK","county":"Texas","geo_location":{"type": "Point", "coordinates": [36.9558,-101.0594]}},
{"zip_code":"73551","country":"US","city":"Hollister","state":"Oklahoma","state_ab":"OK","county":"Tillman","geo_location":{"type": "Point", "coordinates": [34.3525,-98.8814]}},
{"zip_code":"74011","country":"US","city":"Broken Arrow","state":"Oklahoma","state_ab":"OK","county":"Tulsa","geo_location":{"type": "Point", "coordinates": [35.9908,-95.8143]}},
{"zip_code":"74037","country":"US","city":"Jenks","state":"Oklahoma","state_ab":"OK","county":"Tulsa","geo_location":{"type": "Point", "coordinates": [36.0148,-95.9797]}},
{"zip_code":"74101","country":"US","city":"Tulsa","state":"Oklahoma","state_ab":"OK","county":"Tulsa","geo_location":{"type": "Point", "coordinates": [36.0391,-95.8687]}},
{"zip_code":"74114","country":"US","city":"Tulsa","state":"Oklahoma","state_ab":"OK","county":"Tulsa","geo_location":{"type": "Point", "coordinates": [36.1262,-95.9408]}},
{"zip_code":"74141","country":"US","city":"Tulsa","state":"Oklahoma","state_ab":"OK","county":"Tulsa","geo_location":{"type": "Point", "coordinates": [36.1398,-96.0297]}},
{"zip_code":"74194","country":"US","city":"Tulsa","state":"Oklahoma","state_ab":"OK","county":"Tulsa","geo_location":{"type": "Point", "coordinates": [36.1398,-96.0297]}},
{"zip_code":"74477","country":"US","city":"Wagoner","state":"Oklahoma","state_ab":"OK","county":"Wagoner","geo_location":{"type": "Point", "coordinates": [35.9636,-95.5139]}},
{"zip_code":"74051","country":"US","city":"Ochelata","state":"Oklahoma","state_ab":"OK","county":"Washington","geo_location":{"type": "Point", "coordinates": [36.5947,-95.9691]}},
{"zip_code":"73021","country":"US","city":"Colony","state":"Oklahoma","state_ab":"OK","county":"Washita","geo_location":{"type": "Point", "coordinates": [35.3448,-98.6707]}},
{"zip_code":"73641","country":"US","city":"Dill City","state":"Oklahoma","state_ab":"OK","county":"Washita","geo_location":{"type": "Point", "coordinates": [35.2787,-99.1537]}},
{"zip_code":"73717","country":"US","city":"Alva","state":"Oklahoma","state_ab":"OK","county":"Woods","geo_location":{"type": "Point", "coordinates": [36.8016,-98.6722]}},
{"zip_code":"73731","country":"US","city":"Dacoma","state":"Oklahoma","state_ab":"OK","county":"Woods","geo_location":{"type": "Point", "coordinates": [36.6606,-98.5942]}},
{"zip_code":"97814","country":"US","city":"Baker City","state":"Oregon","state_ab":"OR","county":"Baker","geo_location":{"type": "Point", "coordinates": [44.7542,-117.7427]}},
{"zip_code":"97324","country":"US","city":"Alsea","state":"Oregon","state_ab":"OR","county":"Benton","geo_location":{"type": "Point", "coordinates": [44.3691,-123.6089]}},
{"zip_code":"97027","country":"US","city":"Gladstone","state":"Oregon","state_ab":"OR","county":"Clackamas","geo_location":{"type": "Point", "coordinates": [45.3899,-122.5902]}},
{"zip_code":"97067","country":"US","city":"Welches","state":"Oregon","state_ab":"OR","county":"Clackamas","geo_location":{"type": "Point", "coordinates": [45.3399,-121.9598]}},
{"zip_code":"97054","country":"US","city":"Deer Island","state":"Oregon","state_ab":"OR","county":"Columbia","geo_location":{"type": "Point", "coordinates": [45.9356,-122.8985]}},
{"zip_code":"97414","country":"US","city":"Broadbent","state":"Oregon","state_ab":"OR","county":"Coos","geo_location":{"type": "Point", "coordinates": [42.985,-124.1189]}},
{"zip_code":"97751","country":"US","city":"Paulina","state":"Oregon","state_ab":"OR","county":"Crook","geo_location":{"type": "Point", "coordinates": [44.2102,-119.7828]}},
{"zip_code":"97441","country":"US","city":"Gardiner","state":"Oregon","state_ab":"OR","county":"Douglas","geo_location":{"type": "Point", "coordinates": [43.7857,-124.1437]}},
{"zip_code":"97467","country":"US","city":"Reedsport","state":"Oregon","state_ab":"OR","county":"Douglas","geo_location":{"type": "Point", "coordinates": [43.7104,-123.9565]}},
{"zip_code":"97481","country":"US","city":"Tenmile","state":"Oregon","state_ab":"OR","county":"Douglas","geo_location":{"type": "Point", "coordinates": [43.114,-123.5294]}},
{"zip_code":"97494","country":"US","city":"Wilbur","state":"Oregon","state_ab":"OR","county":"Douglas","geo_location":{"type": "Point", "coordinates": [43.3284,-123.3332]}},
{"zip_code":"97904","country":"US","city":"Drewsey","state":"Oregon","state_ab":"OR","county":"Harney","geo_location":{"type": "Point", "coordinates": [43.8643,-118.4707]}},
{"zip_code":"97014","country":"US","city":"Cascade Locks","state":"Oregon","state_ab":"OR","county":"Hood River","geo_location":{"type": "Point", "coordinates": [45.671,-121.8686]}},
{"zip_code":"97041","country":"US","city":"Mount Hood Parkdale","state":"Oregon","state_ab":"OR","county":"Hood River","geo_location":{"type": "Point", "coordinates": [45.4929,-121.5983]}},
{"zip_code":"97504","country":"US","city":"Medford","state":"Oregon","state_ab":"OR","county":"Jackson","geo_location":{"type": "Point", "coordinates": [42.3363,-122.8398]}},
{"zip_code":"97711","country":"US","city":"Ashwood","state":"Oregon","state_ab":"OR","county":"Jefferson","geo_location":{"type": "Point", "coordinates": [44.7195,-120.7192]}},
{"zip_code":"97531","country":"US","city":"Kerby","state":"Oregon","state_ab":"OR","county":"Josephine","geo_location":{"type": "Point", "coordinates": [42.2093,-123.6573]}},
{"zip_code":"97544","country":"US","city":"Williams","state":"Oregon","state_ab":"OR","county":"Josephine","geo_location":{"type": "Point", "coordinates": [42.223,-123.2829]}},
{"zip_code":"97621","country":"US","city":"Beatty","state":"Oregon","state_ab":"OR","county":"Klamath","geo_location":{"type": "Point", "coordinates": [42.4369,-121.22]}},
{"zip_code":"97634","country":"US","city":"Midland","state":"Oregon","state_ab":"OR","county":"Klamath","geo_location":{"type": "Point", "coordinates": [42.1284,-121.871]}},
{"zip_code":"97737","country":"US","city":"Gilchrist","state":"Oregon","state_ab":"OR","county":"Klamath","geo_location":{"type": "Point", "coordinates": [43.3725,-121.6583]}},
{"zip_code":"97401","country":"US","city":"Eugene","state":"Oregon","state_ab":"OR","county":"Lane","geo_location":{"type": "Point", "coordinates": [44.0682,-123.0819]}},
{"zip_code":"97427","country":"US","city":"Culp Creek","state":"Oregon","state_ab":"OR","county":"Lane","geo_location":{"type": "Point", "coordinates": [43.6579,-122.7871]}},
{"zip_code":"97454","country":"US","city":"Marcola","state":"Oregon","state_ab":"OR","county":"Lane","geo_location":{"type": "Point", "coordinates": [44.2064,-122.8246]}},
{"zip_code":"97364","country":"US","city":"Neotsu","state":"Oregon","state_ab":"OR","county":"Lincoln","geo_location":{"type": "Point", "coordinates": [44.9988,-123.9843]}},
{"zip_code":"97391","country":"US","city":"Toledo","state":"Oregon","state_ab":"OR","county":"Lincoln","geo_location":{"type": "Point", "coordinates": [44.6271,-123.9301]}},
{"zip_code":"97377","country":"US","city":"Shedd","state":"Oregon","state_ab":"OR","county":"Linn","geo_location":{"type": "Point", "coordinates": [44.453,-123.1065]}},
{"zip_code":"97917","country":"US","city":"Riverside","state":"Oregon","state_ab":"OR","county":"Malheur","geo_location":{"type": "Point", "coordinates": [43.5099,-118.0986]}},
{"zip_code":"97311","country":"US","city":"Salem","state":"Oregon","state_ab":"OR","county":"Marion","geo_location":{"type": "Point", "coordinates": [44.9438,-123.0286]}},
{"zip_code":"97207","country":"US","city":"Portland","state":"Oregon","state_ab":"OR","county":"Multnomah","geo_location":{"type": "Point", "coordinates": [45.4803,-122.7111]}},
{"zip_code":"97221","country":"US","city":"Portland","state":"Oregon","state_ab":"OR","county":"Multnomah","geo_location":{"type": "Point", "coordinates": [45.4918,-122.7267]}},
{"zip_code":"97351","country":"US","city":"Independence","state":"Oregon","state_ab":"OR","county":"Polk","geo_location":{"type": "Point", "coordinates": [44.8481,-123.1879]}},
{"zip_code":"97131","country":"US","city":"Nehalem","state":"Oregon","state_ab":"OR","county":"Tillamook","geo_location":{"type": "Point", "coordinates": [45.7216,-123.9049]}},
{"zip_code":"97801","country":"US","city":"Pendleton","state":"Oregon","state_ab":"OR","county":"Umatilla","geo_location":{"type": "Point", "coordinates": [45.6605,-118.7831]}},
{"zip_code":"97827","country":"US","city":"Elgin","state":"Oregon","state_ab":"OR","county":"Union","geo_location":{"type": "Point", "coordinates": [45.5941,-117.9112]}},
{"zip_code":"97841","country":"US","city":"Imbler","state":"Oregon","state_ab":"OR","county":"Union","geo_location":{"type": "Point", "coordinates": [45.4599,-117.9544]}},
{"zip_code":"97867","country":"US","city":"North Powder","state":"Oregon","state_ab":"OR","county":"Union","geo_location":{"type": "Point", "coordinates": [45.0317,-117.9337]}},
{"zip_code":"97001","country":"US","city":"Antelope","state":"Oregon","state_ab":"OR","county":"Wasco","geo_location":{"type": "Point", "coordinates": [44.8892,-120.7914]}},
{"zip_code":"97117","country":"US","city":"Gales Creek","state":"Oregon","state_ab":"OR","county":"Washington","geo_location":{"type": "Point", "coordinates": [45.5957,-123.234]}},
{"zip_code":"97144","country":"US","city":"Timber","state":"Oregon","state_ab":"OR","county":"Washington","geo_location":{"type": "Point", "coordinates": [45.727,-123.3119]}},
{"zip_code":"17324","country":"US","city":"Gardners","state":"Pennsylvania","state_ab":"PA","county":"Adams","geo_location":{"type": "Point", "coordinates": [40.0428,-77.1877]}},
{"zip_code":"17337","country":"US","city":"Idaville","state":"Pennsylvania","state_ab":"PA","county":"Adams","geo_location":{"type": "Point", "coordinates": [40.0157,-77.2001]}},
{"zip_code":"15007","country":"US","city":"Bakerstown","state":"Pennsylvania","state_ab":"PA","county":"Allegheny","geo_location":{"type": "Point", "coordinates": [40.6478,-79.931]}},
{"zip_code":"15034","country":"US","city":"Dravosburg","state":"Pennsylvania","state_ab":"PA","county":"Allegheny","geo_location":{"type": "Point", "coordinates": [40.3527,-79.8895]}},
{"zip_code":"15047","country":"US","city":"Greenock","state":"Pennsylvania","state_ab":"PA","county":"Allegheny","geo_location":{"type": "Point", "coordinates": [40.4344,-80.0248]}},
{"zip_code":"15137","country":"US","city":"North Versailles","state":"Pennsylvania","state_ab":"PA","county":"Allegheny","geo_location":{"type": "Point", "coordinates": [40.3762,-79.8124]}},
{"zip_code":"15201","country":"US","city":"Pittsburgh","state":"Pennsylvania","state_ab":"PA","county":"Allegheny","geo_location":{"type": "Point", "coordinates": [40.4752,-79.9528]}},
{"zip_code":"15214","country":"US","city":"Pittsburgh","state":"Pennsylvania","state_ab":"PA","county":"Allegheny","geo_location":{"type": "Point", "coordinates": [40.4865,-80.014]}},
{"zip_code":"15227","country":"US","city":"Pittsburgh","state":"Pennsylvania","state_ab":"PA","county":"Allegheny","geo_location":{"type": "Point", "coordinates": [40.3805,-79.9667]}},
{"zip_code":"15241","country":"US","city":"Pittsburgh","state":"Pennsylvania","state_ab":"PA","county":"Allegheny","geo_location":{"type": "Point", "coordinates": [40.3323,-80.081]}},
{"zip_code":"15254","country":"US","city":"Pittsburgh","state":"Pennsylvania","state_ab":"PA","county":"Allegheny","geo_location":{"type": "Point", "coordinates": [40.4344,-80.0248]}},
{"zip_code":"15267","country":"US","city":"Pittsburgh","state":"Pennsylvania","state_ab":"PA","county":"Allegheny","geo_location":{"type": "Point", "coordinates": [40.4344,-80.0248]}},
{"zip_code":"15281","country":"US","city":"Pittsburgh","state":"Pennsylvania","state_ab":"PA","county":"Allegheny","geo_location":{"type": "Point", "coordinates": [40.4344,-80.0248]}},
{"zip_code":"18444","country":"US","city":"Moscow","state":"Pennsylvania","state_ab":"PA","county":"Lackawanna","geo_location":{"type": "Point", "coordinates": [41.3432,-75.5301]}},
{"zip_code":"18471","country":"US","city":"Waverly","state":"Pennsylvania","state_ab":"PA","county":"Lackawanna","geo_location":{"type": "Point", "coordinates": [41.5238,-75.6906]}},
{"zip_code":"18507","country":"US","city":"Moosic","state":"Pennsylvania","state_ab":"PA","county":"Lackawanna","geo_location":{"type": "Point", "coordinates": [41.3554,-75.6805]}},
{"zip_code":"17504","country":"US","city":"Bausman","state":"Pennsylvania","state_ab":"PA","county":"Lancaster","geo_location":{"type": "Point", "coordinates": [40.024,-76.3281]}},
{"zip_code":"17517","country":"US","city":"Denver","state":"Pennsylvania","state_ab":"PA","county":"Lancaster","geo_location":{"type": "Point", "coordinates": [40.2297,-76.1157]}},
{"zip_code":"17557","country":"US","city":"New Holland","state":"Pennsylvania","state_ab":"PA","county":"Lancaster","geo_location":{"type": "Point", "coordinates": [40.1005,-76.0801]}},
{"zip_code":"17584","country":"US","city":"Willow Street","state":"Pennsylvania","state_ab":"PA","county":"Lancaster","geo_location":{"type": "Point", "coordinates": [39.967,-76.2752]}},
{"zip_code":"17607","country":"US","city":"Lancaster","state":"Pennsylvania","state_ab":"PA","county":"Lancaster","geo_location":{"type": "Point", "coordinates": [40.0185,-76.2976]}},
{"zip_code":"16101","country":"US","city":"New Castle","state":"Pennsylvania","state_ab":"PA","county":"Lawrence","geo_location":{"type": "Point", "coordinates": [40.9922,-80.3284]}},
{"zip_code":"17041","country":"US","city":"Lawn","state":"Pennsylvania","state_ab":"PA","county":"Lebanon","geo_location":{"type": "Point", "coordinates": [40.2236,-76.538]}},
{"zip_code":"17067","country":"US","city":"Myerstown","state":"Pennsylvania","state_ab":"PA","county":"Lebanon","geo_location":{"type": "Point", "coordinates": [40.3789,-76.3143]}},
{"zip_code":"18031","country":"US","city":"Breinigsville","state":"Pennsylvania","state_ab":"PA","county":"Lehigh","geo_location":{"type": "Point", "coordinates": [40.5526,-75.6553]}},
{"zip_code":"18224","country":"US","city":"Freeland","state":"Pennsylvania","state_ab":"PA","county":"Luzerne","geo_location":{"type": "Point", "coordinates": [41.0196,-75.888]}},
{"zip_code":"18251","country":"US","city":"Sybertsville","state":"Pennsylvania","state_ab":"PA","county":"Luzerne","geo_location":{"type": "Point", "coordinates": [41.2722,-75.8801]}},
{"zip_code":"18611","country":"US","city":"Cambra","state":"Pennsylvania","state_ab":"PA","county":"Luzerne","geo_location":{"type": "Point", "coordinates": [41.1103,-75.7755]}},
{"zip_code":"18637","country":"US","city":"Nuangola","state":"Pennsylvania","state_ab":"PA","county":"Luzerne County","geo_location":{"type": "Point", "coordinates": [41.2401,-75.8912]}},
{"zip_code":"18651","country":"US","city":"Plymouth","state":"Pennsylvania","state_ab":"PA","county":"Luzerne","geo_location":{"type": "Point", "coordinates": [41.2458,-75.9481]}},
{"zip_code":"18701","country":"US","city":"Wilkes Barre","state":"Pennsylvania","state_ab":"PA","county":"Luzerne","geo_location":{"type": "Point", "coordinates": [41.2436,-75.885]}},
{"zip_code":"18767","country":"US","city":"Wilkes Barre","state":"Pennsylvania","state_ab":"PA","county":"Luzerne","geo_location":{"type": "Point", "coordinates": [41.2722,-75.8801]}},
{"zip_code":"17737","country":"US","city":"Hughesville","state":"Pennsylvania","state_ab":"PA","county":"Lycoming","geo_location":{"type": "Point", "coordinates": [41.256,-76.7141]}},
{"zip_code":"16114","country":"US","city":"Clarks Mills","state":"Pennsylvania","state_ab":"PA","county":"Mercer","geo_location":{"type": "Point", "coordinates": [41.3851,-80.1752]}},
{"zip_code":"16127","country":"US","city":"Grove City","state":"Pennsylvania","state_ab":"PA","county":"Mercer","geo_location":{"type": "Point", "coordinates": [41.1607,-80.0841]}},
{"zip_code":"16154","country":"US","city":"Transfer","state":"Pennsylvania","state_ab":"PA","county":"Mercer","geo_location":{"type": "Point", "coordinates": [41.3244,-80.4197]}},
{"zip_code":"17054","country":"US","city":"Mattawana","state":"Pennsylvania","state_ab":"PA","county":"Mifflin","geo_location":{"type": "Point", "coordinates": [40.496,-77.7237]}},
{"zip_code":"18301","country":"US","city":"East Stroudsburg","state":"Pennsylvania","state_ab":"PA","county":"Monroe","geo_location":{"type": "Point", "coordinates": [41.0367,-75.1735]}},
{"zip_code":"18327","country":"US","city":"Delaware Water Gap","state":"Pennsylvania","state_ab":"PA","county":"Monroe","geo_location":{"type": "Point", "coordinates": [40.9886,-75.1512]}},
{"zip_code":"18341","country":"US","city":"Minisink Hills","state":"Pennsylvania","state_ab":"PA","county":"Monroe","geo_location":{"type": "Point", "coordinates": [40.9911,-75.2993]}},
{"zip_code":"18354","country":"US","city":"Sciota","state":"Pennsylvania","state_ab":"PA","county":"Monroe","geo_location":{"type": "Point", "coordinates": [40.9257,-75.325]}},
{"zip_code":"18084","country":"US","city":"Sumneytown","state":"Pennsylvania","state_ab":"PA","county":"Montgomery","geo_location":{"type": "Point", "coordinates": [40.3278,-75.454]}},
{"zip_code":"19034","country":"US","city":"Fort Washington","state":"Pennsylvania","state_ab":"PA","county":"Montgomery","geo_location":{"type": "Point", "coordinates": [40.1386,-75.2022]}},
{"zip_code":"19407","country":"US","city":"Audubon","state":"Pennsylvania","state_ab":"PA","county":"Montgomery","geo_location":{"type": "Point", "coordinates": [40.2119,-75.3559]}},
{"zip_code":"19474","country":"US","city":"Skippack","state":"Pennsylvania","state_ab":"PA","county":"Montgomery","geo_location":{"type": "Point", "coordinates": [40.2251,-75.4031]}},
{"zip_code":"18017","country":"US","city":"Bethlehem","state":"Pennsylvania","state_ab":"PA","county":"Northampton","geo_location":{"type": "Point", "coordinates": [40.6622,-75.3903]}},
{"zip_code":"18044","country":"US","city":"Easton","state":"Pennsylvania","state_ab":"PA","county":"Northampton","geo_location":{"type": "Point", "coordinates": [40.6934,-75.4712]}},
{"zip_code":"17777","country":"US","city":"Watsontown","state":"Pennsylvania","state_ab":"PA","county":"Northumberland","geo_location":{"type": "Point", "coordinates": [41.102,-76.8532]}},
{"zip_code":"17801","country":"US","city":"Sunbury","state":"Pennsylvania","state_ab":"PA","county":"Northumberland","geo_location":{"type": "Point", "coordinates": [40.8551,-76.7776]}},
{"zip_code":"17867","country":"US","city":"Rebuck","state":"Pennsylvania","state_ab":"PA","county":"Northumberland","geo_location":{"type": "Point", "coordinates": [40.7141,-76.6886]}},
{"zip_code":"17881","country":"US","city":"Trevorton","state":"Pennsylvania","state_ab":"PA","county":"Northumberland","geo_location":{"type": "Point", "coordinates": [40.7819,-76.6702]}},
{"zip_code":"19111","country":"US","city":"Philadelphia","state":"Pennsylvania","state_ab":"PA","county":"Philadelphia","geo_location":{"type": "Point", "coordinates": [40.0596,-75.0818]}},
{"zip_code":"19124","country":"US","city":"Philadelphia","state":"Pennsylvania","state_ab":"PA","county":"Philadelphia","geo_location":{"type": "Point", "coordinates": [40.0178,-75.0895]}},
{"zip_code":"19137","country":"US","city":"Philadelphia","state":"Pennsylvania","state_ab":"PA","county":"Philadelphia","geo_location":{"type": "Point", "coordinates": [40.0008,-75.0727]}},
{"zip_code":"19151","country":"US","city":"Philadelphia","state":"Pennsylvania","state_ab":"PA","county":"Philadelphia","geo_location":{"type": "Point", "coordinates": [39.9772,-75.2545]}},
{"zip_code":"19177","country":"US","city":"Philadelphia","state":"Pennsylvania","state_ab":"PA","county":"Philadelphia","geo_location":{"type": "Point", "coordinates": [40.0018,-75.1179]}},
{"zip_code":"19191","country":"US","city":"Philadelphia","state":"Pennsylvania","state_ab":"PA","county":"Philadelphia","geo_location":{"type": "Point", "coordinates": [40.0018,-75.1179]}},
{"zip_code":"18457","country":"US","city":"Rowland","state":"Pennsylvania","state_ab":"PA","county":"Pike","geo_location":{"type": "Point", "coordinates": [41.4719,-75.0485]}},
{"zip_code":"16927","country":"US","city":"Harrison Valley","state":"Pennsylvania","state_ab":"PA","county":"Potter","geo_location":{"type": "Point", "coordinates": [41.9587,-77.6587]}},
{"zip_code":"16941","country":"US","city":"Genesee","state":"Pennsylvania","state_ab":"PA","county":"Potter","geo_location":{"type": "Point", "coordinates": [41.9883,-77.758]}},
{"zip_code":"17931","country":"US","city":"Frackville","state":"Pennsylvania","state_ab":"PA","county":"Schuylkill","geo_location":{"type": "Point", "coordinates": [40.7825,-76.2311]}},
{"zip_code":"17944","country":"US","city":"Llewellyn","state":"Pennsylvania","state_ab":"PA","county":"Schuylkill","geo_location":{"type": "Point", "coordinates": [40.6758,-76.2819]}},
{"zip_code":"17957","country":"US","city":"Muir","state":"Pennsylvania","state_ab":"PA","county":"Schuylkill","geo_location":{"type": "Point", "coordinates": [40.5926,-76.5161]}},
{"zip_code":"18211","country":"US","city":"Andreas","state":"Pennsylvania","state_ab":"PA","county":"Schuylkill","geo_location":{"type": "Point", "coordinates": [40.7465,-75.8342]}},
{"zip_code":"18237","country":"US","city":"Mcadoo","state":"Pennsylvania","state_ab":"PA","county":"Schuylkill","geo_location":{"type": "Point", "coordinates": [40.8979,-75.9971]}},
{"zip_code":"17827","country":"US","city":"Freeburg","state":"Pennsylvania","state_ab":"PA","county":"Snyder","geo_location":{"type": "Point", "coordinates": [40.765,-76.9395]}},
{"zip_code":"17841","country":"US","city":"Mc Clure","state":"Pennsylvania","state_ab":"PA","county":"Snyder","geo_location":{"type": "Point", "coordinates": [40.6991,-77.3758]}},
{"zip_code":"15551","country":"US","city":"Markleton","state":"Pennsylvania","state_ab":"PA","county":"Somerset","geo_location":{"type": "Point", "coordinates": [39.8691,-79.2879]}},
{"zip_code":"15564","country":"US","city":"Wellersburg","state":"Pennsylvania","state_ab":"PA","county":"Somerset","geo_location":{"type": "Point", "coordinates": [39.7299,-78.8441]}},
{"zip_code":"15924","country":"US","city":"Cairnbrook","state":"Pennsylvania","state_ab":"PA","county":"Somerset","geo_location":{"type": "Point", "coordinates": [40.1149,-78.7851]}},
{"zip_code":"15937","country":"US","city":"Jerome","state":"Pennsylvania","state_ab":"PA","county":"Somerset","geo_location":{"type": "Point", "coordinates": [40.2084,-78.9873]}},
{"zip_code":"18844","country":"US","city":"Springville","state":"Pennsylvania","state_ab":"PA","county":"Susquehanna","geo_location":{"type": "Point", "coordinates": [41.7147,-75.9025]}},
{"zip_code":"16901","country":"US","city":"Wellsboro","state":"Pennsylvania","state_ab":"PA","county":"Tioga","geo_location":{"type": "Point", "coordinates": [41.7373,-77.308]}},
{"zip_code":"16374","country":"US","city":"Kennerdell","state":"Pennsylvania","state_ab":"PA","county":"Venango","geo_location":{"type": "Point", "coordinates": [41.2848,-79.7393]}},
{"zip_code":"16347","country":"US","city":"Sheffield","state":"Pennsylvania","state_ab":"PA","county":"Warren","geo_location":{"type": "Point", "coordinates": [41.7005,-79.0348]}},
{"zip_code":"15021","country":"US","city":"Burgettstown","state":"Pennsylvania","state_ab":"PA","county":"Washington","geo_location":{"type": "Point", "coordinates": [40.3821,-80.4044]}},
{"zip_code":"15317","country":"US","city":"Canonsburg","state":"Pennsylvania","state_ab":"PA","county":"Washington","geo_location":{"type": "Point", "coordinates": [40.2706,-80.1668]}},
{"zip_code":"15331","country":"US","city":"Ellsworth","state":"Pennsylvania","state_ab":"PA","county":"Washington","geo_location":{"type": "Point", "coordinates": [40.1073,-80.0204]}},
{"zip_code":"15434","country":"US","city":"Elco","state":"Pennsylvania","state_ab":"PA","county":"Washington","geo_location":{"type": "Point", "coordinates": [40.0797,-79.8758]}},
{"zip_code":"18417","country":"US","city":"Equinunk","state":"Pennsylvania","state_ab":"PA","county":"Wayne","geo_location":{"type": "Point", "coordinates": [41.8117,-75.1891]}},
{"zip_code":"18431","country":"US","city":"Honesdale","state":"Pennsylvania","state_ab":"PA","county":"Wayne","geo_location":{"type": "Point", "coordinates": [41.5792,-75.2528]}},
{"zip_code":"15087","country":"US","city":"Webster","state":"Pennsylvania","state_ab":"PA","county":"Westmoreland","geo_location":{"type": "Point", "coordinates": [40.3602,-79.4398]}},
{"zip_code":"15601","country":"US","city":"Greensburg","state":"Pennsylvania","state_ab":"PA","county":"Westmoreland","geo_location":{"type": "Point", "coordinates": [40.3074,-79.5424]}},
{"zip_code":"15627","country":"US","city":"Derry","state":"Pennsylvania","state_ab":"PA","county":"Westmoreland","geo_location":{"type": "Point", "coordinates": [40.3349,-79.3326]}},
{"zip_code":"15641","country":"US","city":"Hyde Park","state":"Pennsylvania","state_ab":"PA","county":"Westmoreland","geo_location":{"type": "Point", "coordinates": [40.6311,-79.5899]}},
{"zip_code":"17311","country":"US","city":"Codorus","state":"Pennsylvania","state_ab":"PA","county":"York","geo_location":{"type": "Point", "coordinates": [39.8718,-76.7599]}},
{"zip_code":"17364","country":"US","city":"Thomasville","state":"Pennsylvania","state_ab":"PA","county":"York","geo_location":{"type": "Point", "coordinates": [39.9346,-76.8822]}},
{"zip_code":"17401","country":"US","city":"York","state":"Pennsylvania","state_ab":"PA","county":"York","geo_location":{"type": "Point", "coordinates": [39.9635,-76.7269]}},
{"zip_code":"2887","country":"US","city":"Warwick","state":"Rhode Island","state_ab":"RI","county":"Kent","geo_location":{"type": "Point", "coordinates": [41.6825,-71.5577]}},
{"zip_code":"2861","country":"US","city":"Pawtucket","state":"Rhode Island","state_ab":"RI","county":"Providence","geo_location":{"type": "Point", "coordinates": [41.8814,-71.356]}},
{"zip_code":"2911","country":"US","city":"North Providence","state":"Rhode Island","state_ab":"RI","county":"Providence","geo_location":{"type": "Point", "coordinates": [41.8547,-71.4735]}},
{"zip_code":"2807","country":"US","city":"Block Island","state":"Rhode Island","state_ab":"RI","county":"Washington","geo_location":{"type": "Point", "coordinates": [41.1715,-71.5748]}},
{"zip_code":"2874","country":"US","city":"Saunderstown","state":"Rhode Island","state_ab":"RI","county":"Washington","geo_location":{"type": "Point", "coordinates": [41.5105,-71.4427]}},
{"zip_code":"29851","country":"US","city":"Warrenville","state":"South Carolina","state_ab":"SC","county":"Aiken","geo_location":{"type": "Point", "coordinates": [33.526,-81.7956]}},
{"zip_code":"29684","country":"US","city":"Starr","state":"South Carolina","state_ab":"SC","county":"Anderson","geo_location":{"type": "Point", "coordinates": [34.3962,-82.6897]}},
{"zip_code":"29697","country":"US","city":"Williamston","state":"South Carolina","state_ab":"SC","county":"Anderson","geo_location":{"type": "Point", "coordinates": [34.6206,-82.511]}},
{"zip_code":"29901","country":"US","city":"Beaufort","state":"South Carolina","state_ab":"SC","county":"Beaufort","geo_location":{"type": "Point", "coordinates": [32.4244,-80.5653]}},
{"zip_code":"29914","country":"US","city":"Dale","state":"South Carolina","state_ab":"SC","county":"Beaufort","geo_location":{"type": "Point", "coordinates": [32.5527,-80.677]}},
{"zip_code":"29941","country":"US","city":"Sheldon","state":"South Carolina","state_ab":"SC","county":"Beaufort","geo_location":{"type": "Point", "coordinates": [32.5431,-80.8126]}},
{"zip_code":"29077","country":"US","city":"Lone Star","state":"South Carolina","state_ab":"SC","county":"Calhoun County","geo_location":{"type": "Point", "coordinates": [33.6799,-80.6413]}},
{"zip_code":"29411","country":"US","city":"Charleston","state":"South Carolina","state_ab":"SC","county":"Charleston County","geo_location":{"type": "Point", "coordinates": [32.8715,-79.9947]}},
{"zip_code":"29424","country":"US","city":"Charleston","state":"South Carolina","state_ab":"SC","county":"Charleston","geo_location":{"type": "Point", "coordinates": [32.7831,-79.937]}},
{"zip_code":"29451","country":"US","city":"Isle Of Palms","state":"South Carolina","state_ab":"SC","county":"Charleston","geo_location":{"type": "Point", "coordinates": [32.7943,-79.7729]}},
{"zip_code":"29464","country":"US","city":"Mount Pleasant","state":"South Carolina","state_ab":"SC","county":"Charleston","geo_location":{"type": "Point", "coordinates": [32.8473,-79.8206]}},
{"zip_code":"29101","country":"US","city":"Mc Bee","state":"South Carolina","state_ab":"SC","county":"Chesterfield","geo_location":{"type": "Point", "coordinates": [34.4606,-80.2544]}},
{"zip_code":"29051","country":"US","city":"Gable","state":"South Carolina","state_ab":"SC","county":"Clarendon","geo_location":{"type": "Point", "coordinates": [33.8644,-80.1276]}},
{"zip_code":"29567","country":"US","city":"Little Rock","state":"South Carolina","state_ab":"SC","county":"Dillon","geo_location":{"type": "Point", "coordinates": [34.5613,-79.4335]}},
{"zip_code":"29437","country":"US","city":"Dorchester","state":"South Carolina","state_ab":"SC","county":"Dorchester","geo_location":{"type": "Point", "coordinates": [33.1247,-80.4034]}},
{"zip_code":"29477","country":"US","city":"Saint George","state":"South Carolina","state_ab":"SC","county":"Dorchester","geo_location":{"type": "Point", "coordinates": [33.1845,-80.5732]}},
{"zip_code":"29824","country":"US","city":"Edgefield","state":"South Carolina","state_ab":"SC","county":"Edgefield","geo_location":{"type": "Point", "coordinates": [33.8056,-81.966]}},
{"zip_code":"29114","country":"US","city":"Olanta","state":"South Carolina","state_ab":"SC","county":"Florence","geo_location":{"type": "Point", "coordinates": [33.9285,-79.9153]}},
{"zip_code":"29501","country":"US","city":"Florence","state":"South Carolina","state_ab":"SC","county":"Florence","geo_location":{"type": "Point", "coordinates": [34.1838,-79.7728]}},
{"zip_code":"29541","country":"US","city":"Effingham","state":"South Carolina","state_ab":"SC","county":"Florence","geo_location":{"type": "Point", "coordinates": [34.0946,-79.7918]}},
{"zip_code":"29604","country":"US","city":"Greenville","state":"South Carolina","state_ab":"SC","county":"Greenville","geo_location":{"type": "Point", "coordinates": [34.8497,-82.4538]}},
{"zip_code":"29617","country":"US","city":"Greenville","state":"South Carolina","state_ab":"SC","county":"Greenville","geo_location":{"type": "Point", "coordinates": [34.912,-82.4666]}},
{"zip_code":"29644","country":"US","city":"Fountain Inn","state":"South Carolina","state_ab":"SC","county":"Greenville","geo_location":{"type": "Point", "coordinates": [34.6578,-82.2441]}},
{"zip_code":"29527","country":"US","city":"Conway","state":"South Carolina","state_ab":"SC","county":"Horry","geo_location":{"type": "Point", "coordinates": [33.7827,-79.1473]}},
{"zip_code":"29581","country":"US","city":"Nichols","state":"South Carolina","state_ab":"SC","county":"Horry","geo_location":{"type": "Point", "coordinates": [34.2426,-79.1625]}},
{"zip_code":"29927","country":"US","city":"Hardeeville","state":"South Carolina","state_ab":"SC","county":"Jasper","geo_location":{"type": "Point", "coordinates": [32.2635,-81.0669]}},
{"zip_code":"29707","country":"US","city":"Fort Mill","state":"South Carolina","state_ab":"SC","county":"Lancaster County","geo_location":{"type": "Point", "coordinates": [34.9773,-80.8584]}},
{"zip_code":"29721","country":"US","city":"Lancaster","state":"South Carolina","state_ab":"SC","county":"Lancaster","geo_location":{"type": "Point", "coordinates": [34.6994,-80.7817]}},
{"zip_code":"29594","country":"US","city":"Tatum","state":"South Carolina","state_ab":"SC","county":"Marlboro","geo_location":{"type": "Point", "coordinates": [34.6405,-79.5869]}},
{"zip_code":"29037","country":"US","city":"Chappells","state":"South Carolina","state_ab":"SC","county":"Newberry","geo_location":{"type": "Point", "coordinates": [34.1856,-81.8644]}},
{"zip_code":"29127","country":"US","city":"Prosperity","state":"South Carolina","state_ab":"SC","county":"Newberry","geo_location":{"type": "Point", "coordinates": [34.1832,-81.5324]}},
{"zip_code":"29631","country":"US","city":"Clemson","state":"South Carolina","state_ab":"SC","county":"Pickens","geo_location":{"type": "Point", "coordinates": [34.6831,-82.825]}},
{"zip_code":"29657","country":"US","city":"Liberty","state":"South Carolina","state_ab":"SC","county":"Pickens","geo_location":{"type": "Point", "coordinates": [34.7872,-82.6974]}},
{"zip_code":"29671","country":"US","city":"Pickens","state":"South Carolina","state_ab":"SC","county":"Pickens","geo_location":{"type": "Point", "coordinates": [34.9024,-82.7058]}},
{"zip_code":"29204","country":"US","city":"Columbia","state":"South Carolina","state_ab":"SC","county":"Richland","geo_location":{"type": "Point", "coordinates": [34.026,-81.0046]}},
{"zip_code":"29217","country":"US","city":"Columbia","state":"South Carolina","state_ab":"SC","county":"Richland","geo_location":{"type": "Point", "coordinates": [34.006,-80.9708]}},
{"zip_code":"29307","country":"US","city":"Spartanburg","state":"South Carolina","state_ab":"SC","county":"Spartanburg","geo_location":{"type": "Point", "coordinates": [34.9839,-81.8313]}},
{"zip_code":"29334","country":"US","city":"Duncan","state":"South Carolina","state_ab":"SC","county":"Spartanburg","geo_location":{"type": "Point", "coordinates": [34.9176,-82.1258]}},
{"zip_code":"29374","country":"US","city":"Pauline","state":"South Carolina","state_ab":"SC","county":"Spartanburg","geo_location":{"type": "Point", "coordinates": [34.7855,-81.8492]}},
{"zip_code":"29154","country":"US","city":"Sumter","state":"South Carolina","state_ab":"SC","county":"Sumter","geo_location":{"type": "Point", "coordinates": [33.8821,-80.4028]}},
{"zip_code":"29321","country":"US","city":"Buffalo","state":"South Carolina","state_ab":"SC","county":"Union","geo_location":{"type": "Point", "coordinates": [34.7247,-81.6826]}},
{"zip_code":"29554","country":"US","city":"Hemingway","state":"South Carolina","state_ab":"SC","county":"Williamsburg","geo_location":{"type": "Point", "coordinates": [33.7419,-79.4489]}},
{"zip_code":"29734","country":"US","city":"Rock Hill","state":"South Carolina","state_ab":"SC","county":"York","geo_location":{"type": "Point", "coordinates": [34.9926,-81.1787]}},
{"zip_code":"57324","country":"US","city":"Cavour","state":"South Dakota","state_ab":"SD","county":"Beadle","geo_location":{"type": "Point", "coordinates": [44.365,-98.0208]}},
{"zip_code":"57401","country":"US","city":"Aberdeen","state":"South Dakota","state_ab":"SD","county":"Brown","geo_location":{"type": "Point", "coordinates": [45.4661,-98.4856]}},
{"zip_code":"57427","country":"US","city":"Bath","state":"South Dakota","state_ab":"SD","county":"Brown","geo_location":{"type": "Point", "coordinates": [45.4564,-98.3552]}},
{"zip_code":"57441","country":"US","city":"Frederick","state":"South Dakota","state_ab":"SD","county":"Brown","geo_location":{"type": "Point", "coordinates": [45.8493,-98.5176]}},
{"zip_code":"57481","country":"US","city":"Westport","state":"South Dakota","state_ab":"SD","county":"Brown","geo_location":{"type": "Point", "coordinates": [45.6705,-98.5802]}},
{"zip_code":"57621","country":"US","city":"Bullhead","state":"South Dakota","state_ab":"SD","county":"Corson","geo_location":{"type": "Point", "coordinates": [45.8476,-101.0997]}},
{"zip_code":"57634","country":"US","city":"Keldron","state":"South Dakota","state_ab":"SD","county":"Corson","geo_location":{"type": "Point", "coordinates": [45.7528,-101.8843]}},
{"zip_code":"57261","country":"US","city":"Roslyn","state":"South Dakota","state_ab":"SD","county":"Day","geo_location":{"type": "Point", "coordinates": [45.5006,-97.5401]}},
{"zip_code":"57274","country":"US","city":"Webster","state":"South Dakota","state_ab":"SD","county":"Day","geo_location":{"type": "Point", "coordinates": [45.3151,-97.5254]}},
{"zip_code":"57647","country":"US","city":"Parade","state":"South Dakota","state_ab":"SD","county":"Dewey","geo_location":{"type": "Point", "coordinates": [45.0987,-100.8792]}},
{"zip_code":"57661","country":"US","city":"Whitehorse","state":"South Dakota","state_ab":"SD","county":"Dewey","geo_location":{"type": "Point", "coordinates": [45.0987,-100.8792]}},
{"zip_code":"57364","country":"US","city":"New Holland","state":"South Dakota","state_ab":"SD","county":"Douglas","geo_location":{"type": "Point", "coordinates": [43.4291,-98.6069]}},
{"zip_code":"57467","country":"US","city":"Orient","state":"South Dakota","state_ab":"SD","county":"Faulk","geo_location":{"type": "Point", "coordinates": [44.8343,-99.1058]}},
{"zip_code":"57571","country":"US","city":"Saint Charles","state":"South Dakota","state_ab":"SD","county":"Gregory","geo_location":{"type": "Point", "coordinates": [43.0852,-99.0925]}},
{"zip_code":"57221","country":"US","city":"Bryant","state":"South Dakota","state_ab":"SD","county":"Hamlin","geo_location":{"type": "Point", "coordinates": [44.5987,-97.4537]}},
{"zip_code":"57234","country":"US","city":"Estelline","state":"South Dakota","state_ab":"SD","county":"Hamlin","geo_location":{"type": "Point", "coordinates": [44.6029,-96.8928]}},
{"zip_code":"57311","country":"US","city":"Alexandria","state":"South Dakota","state_ab":"SD","county":"Hanson","geo_location":{"type": "Point", "coordinates": [43.6684,-97.7563]}},
{"zip_code":"57724","country":"US","city":"Camp Crook","state":"South Dakota","state_ab":"SD","county":"Harding","geo_location":{"type": "Point", "coordinates": [45.6402,-104.0278]}},
{"zip_code":"57531","country":"US","city":"Draper","state":"South Dakota","state_ab":"SD","county":"Jones","geo_location":{"type": "Point", "coordinates": [43.926,-100.5085]}},
{"zip_code":"57054","country":"US","city":"Ramona","state":"South Dakota","state_ab":"SD","county":"Lake","geo_location":{"type": "Point", "coordinates": [44.1229,-97.2349]}},
{"zip_code":"57027","country":"US","city":"Fairview","state":"South Dakota","state_ab":"SD","county":"Lincoln","geo_location":{"type": "Point", "coordinates": [43.197,-96.5135]}},
{"zip_code":"57544","country":"US","city":"Kennebec","state":"South Dakota","state_ab":"SD","county":"Lyman","geo_location":{"type": "Point", "coordinates": [43.8921,-99.8502]}},
{"zip_code":"57247","country":"US","city":"Lake City","state":"South Dakota","state_ab":"SD","county":"Marshall","geo_location":{"type": "Point", "coordinates": [45.6899,-97.3481]}},
{"zip_code":"57454","country":"US","city":"Langford","state":"South Dakota","state_ab":"SD","county":"Marshall","geo_location":{"type": "Point", "coordinates": [45.6174,-97.7925]}},
{"zip_code":"57737","country":"US","city":"Enning","state":"South Dakota","state_ab":"SD","county":"Meade","geo_location":{"type": "Point", "coordinates": [44.5898,-102.7872]}},
{"zip_code":"57777","country":"US","city":"Red Owl","state":"South Dakota","state_ab":"SD","county":"Meade","geo_location":{"type": "Point", "coordinates": [44.691,-102.587]}},
{"zip_code":"57337","country":"US","city":"Fedora","state":"South Dakota","state_ab":"SD","county":"Miner","geo_location":{"type": "Point", "coordinates": [43.9841,-97.789]}},
{"zip_code":"57041","country":"US","city":"Lyons","state":"South Dakota","state_ab":"SD","county":"Minnehaha","geo_location":{"type": "Point", "coordinates": [43.7285,-96.8709]}},
{"zip_code":"57104","country":"US","city":"Sioux Falls","state":"South Dakota","state_ab":"SD","county":"Minnehaha","geo_location":{"type": "Point", "coordinates": [43.5514,-96.7375]}},
{"zip_code":"57117","country":"US","city":"Sioux Falls","state":"South Dakota","state_ab":"SD","county":"Minnehaha","geo_location":{"type": "Point", "coordinates": [43.6746,-96.7913]}},
{"zip_code":"57197","country":"US","city":"Sioux Falls","state":"South Dakota","state_ab":"SD","county":"Minnehaha","geo_location":{"type": "Point", "coordinates": [43.6746,-96.7913]}},
{"zip_code":"57751","country":"US","city":"Keystone","state":"South Dakota","state_ab":"SD","county":"Pennington","geo_location":{"type": "Point", "coordinates": [43.8848,-103.3995]}},
{"zip_code":"57791","country":"US","city":"Wasta","state":"South Dakota","state_ab":"SD","county":"Pennington","geo_location":{"type": "Point", "coordinates": [44.225,-102.4311]}},
{"zip_code":"57764","country":"US","city":"Oglala","state":"South Dakota","state_ab":"SD","county":"Shannon","geo_location":{"type": "Point", "coordinates": [43.3526,-102.5411]}},
{"zip_code":"57557","country":"US","city":"Mission Ridge","state":"South Dakota","state_ab":"SD","county":"Stanley","geo_location":{"type": "Point", "coordinates": [44.4758,-100.5295]}},
{"zip_code":"57584","country":"US","city":"Witten","state":"South Dakota","state_ab":"SD","county":"Tripp","geo_location":{"type": "Point", "coordinates": [43.4498,-100.0783]}},
{"zip_code":"57014","country":"US","city":"Centerville","state":"South Dakota","state_ab":"SD","county":"Turner","geo_location":{"type": "Point", "coordinates": [43.1176,-96.9636]}},
{"zip_code":"57001","country":"US","city":"Alcester","state":"South Dakota","state_ab":"SD","county":"Union","geo_location":{"type": "Point", "coordinates": [43.0047,-96.6332]}},
{"zip_code":"57067","country":"US","city":"Utica","state":"South Dakota","state_ab":"SD","county":"Yankton","geo_location":{"type": "Point", "coordinates": [43.0164,-97.3694]}},
{"zip_code":"37717","country":"US","city":"Clinton","state":"Tennessee","state_ab":"TN","county":"Anderson","geo_location":{"type": "Point", "coordinates": [36.11,-84.1672]}},
{"zip_code":"37757","country":"US","city":"Jacksboro","state":"Tennessee","state_ab":"TN","county":"Campbell","geo_location":{"type": "Point", "coordinates": [36.3266,-84.1928]}},
{"zip_code":"37847","country":"US","city":"Pioneer","state":"Tennessee","state_ab":"TN","county":"Campbell","geo_location":{"type": "Point", "coordinates": [36.4695,-84.2907]}},
{"zip_code":"38321","country":"US","city":"Cedar Grove","state":"Tennessee","state_ab":"TN","county":"Carroll","geo_location":{"type": "Point", "coordinates": [35.8613,-88.5517]}},
{"zip_code":"38387","country":"US","city":"Westport","state":"Tennessee","state_ab":"TN","county":"Carroll","geo_location":{"type": "Point", "coordinates": [35.8845,-88.2892]}},
{"zip_code":"37694","country":"US","city":"Watauga","state":"Tennessee","state_ab":"TN","county":"Carter","geo_location":{"type": "Point", "coordinates": [36.3702,-82.2683]}},
{"zip_code":"38347","country":"US","city":"Jacks Creek","state":"Tennessee","state_ab":"TN","county":"Chester","geo_location":{"type": "Point", "coordinates": [35.4782,-88.5019]}},
{"zip_code":"37821","country":"US","city":"Newport","state":"Tennessee","state_ab":"TN","county":"Cocke","geo_location":{"type": "Point", "coordinates": [35.9544,-83.2027]}},
{"zip_code":"37201","country":"US","city":"Nashville","state":"Tennessee","state_ab":"TN","county":"Davidson","geo_location":{"type": "Point", "coordinates": [36.1657,-86.7781]}},
{"zip_code":"37214","country":"US","city":"Nashville","state":"Tennessee","state_ab":"TN","county":"Davidson","geo_location":{"type": "Point", "coordinates": [36.1633,-86.6609]}},
{"zip_code":"37227","country":"US","city":"Nashville","state":"Tennessee","state_ab":"TN","county":"Davidson","geo_location":{"type": "Point", "coordinates": [36.1866,-86.7852]}},
{"zip_code":"37241","country":"US","city":"Nashville","state":"Tennessee","state_ab":"TN","county":"Davidson","geo_location":{"type": "Point", "coordinates": [36.1866,-86.7852]}},
{"zip_code":"38374","country":"US","city":"Scotts Hill","state":"Tennessee","state_ab":"TN","county":"Decatur","geo_location":{"type": "Point", "coordinates": [35.505,-88.2405]}},
{"zip_code":"38024","country":"US","city":"Dyersburg","state":"Tennessee","state_ab":"TN","county":"Dyer","geo_location":{"type": "Point", "coordinates": [36.0444,-89.3836]}},
{"zip_code":"38477","country":"US","city":"Prospect","state":"Tennessee","state_ab":"TN","county":"Giles","geo_location":{"type": "Point", "coordinates": [35.0666,-87.0174]}},
{"zip_code":"37861","country":"US","city":"Rutledge","state":"Tennessee","state_ab":"TN","county":"Grainger","geo_location":{"type": "Point", "coordinates": [36.2501,-83.5125]}},
{"zip_code":"37641","country":"US","city":"Chuckey","state":"Tennessee","state_ab":"TN","county":"Greene","geo_location":{"type": "Point", "coordinates": [36.2569,-82.6905]}},
{"zip_code":"37744","country":"US","city":"Greeneville","state":"Tennessee","state_ab":"TN","county":"Greene","geo_location":{"type": "Point", "coordinates": [36.1683,-82.8548]}},
{"zip_code":"37304","country":"US","city":"Bakewell","state":"Tennessee","state_ab":"TN","county":"Hamilton","geo_location":{"type": "Point", "coordinates": [35.3452,-85.138]}},
{"zip_code":"37384","country":"US","city":"Soddy Daisy","state":"Tennessee","state_ab":"TN","county":"Hamilton","geo_location":{"type": "Point", "coordinates": [35.2211,-85.2091]}},
{"zip_code":"37407","country":"US","city":"Chattanooga","state":"Tennessee","state_ab":"TN","county":"Hamilton","geo_location":{"type": "Point", "coordinates": [35.0024,-85.2849]}},
{"zip_code":"37421","country":"US","city":"Chattanooga","state":"Tennessee","state_ab":"TN","county":"Hamilton","geo_location":{"type": "Point", "coordinates": [35.025,-85.1459]}},
{"zip_code":"38361","country":"US","city":"Morris Chapel","state":"Tennessee","state_ab":"TN","county":"Hardin","geo_location":{"type": "Point", "coordinates": [35.3026,-88.3176]}},
{"zip_code":"37731","country":"US","city":"Eidson","state":"Tennessee","state_ab":"TN","county":"Hawkins","geo_location":{"type": "Point", "coordinates": [36.4995,-83.0827]}},
{"zip_code":"38231","country":"US","city":"Henry","state":"Tennessee","state_ab":"TN","county":"Henry","geo_location":{"type": "Point", "coordinates": [36.2013,-88.4536]}},
{"zip_code":"37137","country":"US","city":"Nunnelly","state":"Tennessee","state_ab":"TN","county":"Hickman","geo_location":{"type": "Point", "coordinates": [35.8763,-87.5067]}},
{"zip_code":"37061","country":"US","city":"Erin","state":"Tennessee","state_ab":"TN","county":"Houston","geo_location":{"type": "Point", "coordinates": [36.3067,-87.679]}},
{"zip_code":"37924","country":"US","city":"Knoxville","state":"Tennessee","state_ab":"TN","county":"Knox","geo_location":{"type": "Point", "coordinates": [36.032,-83.8021]}},
{"zip_code":"38077","country":"US","city":"Wynnburg","state":"Tennessee","state_ab":"TN","county":"Lake","geo_location":{"type": "Point", "coordinates": [36.3281,-89.4744]}},
{"zip_code":"38037","country":"US","city":"Gates","state":"Tennessee","state_ab":"TN","county":"Lauderdale","geo_location":{"type": "Point", "coordinates": [35.796,-89.3938]}},
{"zip_code":"38464","country":"US","city":"Lawrenceburg","state":"Tennessee","state_ab":"TN","county":"Lawrence","geo_location":{"type": "Point", "coordinates": [35.2507,-87.3526]}},
{"zip_code":"37771","country":"US","city":"Lenoir City","state":"Tennessee","state_ab":"TN","county":"Loudon","geo_location":{"type": "Point", "coordinates": [35.8104,-84.2665]}},
{"zip_code":"37331","country":"US","city":"Etowah","state":"Tennessee","state_ab":"TN","county":"McMinn","geo_location":{"type": "Point", "coordinates": [35.3314,-84.5283]}},
{"zip_code":"37371","country":"US","city":"Athens","state":"Tennessee","state_ab":"TN","county":"McMinn","geo_location":{"type": "Point", "coordinates": [35.4414,-84.6416]}},
{"zip_code":"38334","country":"US","city":"Finger","state":"Tennessee","state_ab":"TN","county":"McNairy","geo_location":{"type": "Point", "coordinates": [35.3544,-88.5876]}},
{"zip_code":"37397","country":"US","city":"Whitwell","state":"Tennessee","state_ab":"TN","county":"Marion","geo_location":{"type": "Point", "coordinates": [35.1972,-85.5011]}},
{"zip_code":"37034","country":"US","city":"Chapel Hill","state":"Tennessee","state_ab":"TN","county":"Marshall","geo_location":{"type": "Point", "coordinates": [35.6354,-86.6836]}}]}